{
  "date": "2026-07-06T20",
  "generatedAt": "2026-07-06T20:10:08.718Z",
  "source": "coingecko",
  "sectors": [
    {
      "id": "btc",
      "name": "BTC",
      "totalMarketCap": 1274844635236,
      "weightedReturnPct": 0.0129824,
      "weightedAmplitude": 0.0414092176266323,
      "weightedVolatility": 0.02070460881331615,
      "weightedReturnPct7d": 0.056184488489779014,
      "weightedReturnPct30d": 0.04841062683178194,
      "coins": [
        {
          "id": "bitcoin",
          "symbol": "BTC",
          "name": "Bitcoin",
          "marketCap": 1274844635236,
          "open": 62752.324225968776,
          "high": 63879,
          "low": 61339,
          "close": 63567,
          "returnPct": 0.0129824,
          "amplitude": 0.0414092176266323,
          "volatility": 0.02070460881331615,
          "returnPct7d": 0.056184488489779014,
          "returnPct30d": 0.04841062683178194,
          "isMainstream": true
        }
      ]
    },
    {
      "id": "l1",
      "name": "Layer 1 主流",
      "totalMarketCap": 466639018893,
      "weightedReturnPct": 0.001833607409405342,
      "weightedAmplitude": 0.03892059934990221,
      "weightedVolatility": 0.019460299674951106,
      "weightedReturnPct7d": 0.08172942521357336,
      "weightedReturnPct30d": 0.11988158628840358,
      "coins": [
        {
          "id": "ethereum",
          "symbol": "ETH",
          "name": "Ethereum",
          "marketCap": 215800201213,
          "open": 1780.176164832284,
          "high": 1800.61,
          "low": 1732.1,
          "close": 1788.07,
          "returnPct": 0.0044342999999999995,
          "amplitude": 0.039553143582933936,
          "volatility": 0.019776571791466968,
          "returnPct7d": 0.1049373730632385,
          "returnPct30d": 0.15004974312137287,
          "isMainstream": true
        },
        {
          "id": "solana",
          "symbol": "SOL",
          "name": "Solana",
          "marketCap": 47518749048,
          "open": 81.02473295829665,
          "high": 82.17,
          "low": 79.31,
          "close": 81.76,
          "returnPct": 0.0090746,
          "amplitude": 0.03606102635228847,
          "volatility": 0.018030513176144236,
          "returnPct7d": 0.08381780112865579,
          "returnPct30d": 0.3250103360111638,
          "isMainstream": true
        },
        {
          "id": "binancecoin",
          "symbol": "BNB",
          "name": "BNB",
          "marketCap": 78686954275,
          "open": 589.3221997175946,
          "high": 591.99,
          "low": 570.22,
          "close": 583.76,
          "returnPct": -0.0094383,
          "amplitude": 0.03817824699238881,
          "volatility": 0.019089123496194405,
          "returnPct7d": 0.04200115310127448,
          "returnPct30d": 0.017365192619317335,
          "isMainstream": true
        },
        {
          "id": "ripple",
          "symbol": "XRP",
          "name": "XRP",
          "marketCap": 71140059067,
          "open": 1.133291931726915,
          "high": 1.16,
          "low": 1.11,
          "close": 1.14,
          "returnPct": 0.0059191,
          "amplitude": 0.04504504504504481,
          "volatility": 0.022522522522522403,
          "returnPct7d": 0.06701346541854057,
          "returnPct30d": 0.056606245073534046,
          "isMainstream": true
        },
        {
          "id": "cardano",
          "symbol": "ADA",
          "name": "Cardano",
          "marketCap": 6830404928,
          "open": 0.18888131492292845,
          "high": 0.19175,
          "low": 0.178499,
          "close": 0.183296,
          "returnPct": -0.029570500000000003,
          "amplitude": 0.07423571000397766,
          "volatility": 0.03711785500198883,
          "returnPct7d": 0.24386986224643287,
          "returnPct30d": 0.16859458312012002,
          "isMainstream": true
        },
        {
          "id": "avalanche-2",
          "symbol": "AVAX",
          "name": "Avalanche",
          "marketCap": 2988957915,
          "open": 6.89724048584481,
          "high": 6.98,
          "low": 6.72,
          "close": 6.92,
          "returnPct": 0.0032998,
          "amplitude": 0.038690476190476275,
          "volatility": 0.019345238095238138,
          "returnPct7d": 0.030790851183165015,
          "returnPct30d": 0.046594532942367234,
          "isMainstream": true
        },
        {
          "id": "tron",
          "symbol": "TRX",
          "name": "TRON",
          "marketCap": 31140061442,
          "open": 0.328059778129528,
          "high": 0.329784,
          "low": 0.326248,
          "close": 0.328272,
          "returnPct": 0.0006469,
          "amplitude": 0.010838380618425347,
          "volatility": 0.005419190309212674,
          "returnPct7d": 0.022120854536546913,
          "returnPct30d": 0.018772859938477365,
          "isMainstream": true
        },
        {
          "id": "the-open-network",
          "symbol": "GRAM",
          "name": "Gram (prev. Toncoin)",
          "marketCap": 4795246435,
          "open": 1.7968569500742275,
          "high": 1.8,
          "low": 1.7,
          "close": 1.76,
          "returnPct": -0.0205119,
          "amplitude": 0.05882352941176472,
          "volatility": 0.02941176470588236,
          "returnPct7d": 0.0880520770345695,
          "returnPct30d": 0.09852044515702789,
          "isMainstream": true
        },
        {
          "id": "polkadot",
          "symbol": "DOT",
          "name": "Polkadot",
          "marketCap": 1499714494,
          "open": 0.8813215861045952,
          "high": 0.894117,
          "low": 0.851522,
          "close": 0.886271,
          "returnPct": 0.0056159,
          "amplitude": 0.05002219555102516,
          "volatility": 0.02501109777551258,
          "returnPct7d": 0.06762018407819446,
          "returnPct30d": -0.04950177271698533,
          "isMainstream": true
        },
        {
          "id": "sui",
          "symbol": "SUI",
          "name": "Sui",
          "marketCap": 3025953500,
          "open": 0.7554848041975392,
          "high": 0.764279,
          "low": 0.721462,
          "close": 0.746655,
          "returnPct": -0.0116876,
          "amplitude": 0.05934754706415579,
          "volatility": 0.029673773532077896,
          "returnPct7d": 0.0604727347793504,
          "returnPct30d": 0.056769586844433235,
          "isMainstream": true
        },
        {
          "id": "aptos",
          "symbol": "APT",
          "name": "Aptos",
          "marketCap": 524636672,
          "open": 0.6285725639271222,
          "high": 0.637467,
          "low": 0.604181,
          "close": 0.629562,
          "returnPct": 0.0015741,
          "amplitude": 0.055092761937234114,
          "volatility": 0.027546380968617057,
          "returnPct7d": 0.07199727349634387,
          "returnPct30d": -0.029374023545787484,
          "isMainstream": true
        },
        {
          "id": "near",
          "symbol": "NEAR",
          "name": "NEAR Protocol",
          "marketCap": 2688079904,
          "open": 2.006166587809136,
          "high": 2.09,
          "low": 1.96,
          "close": 2.07,
          "returnPct": 0.0318186,
          "amplitude": 0.06632653061224492,
          "volatility": 0.03316326530612246,
          "returnPct7d": 0.09167179373484097,
          "returnPct30d": 0.10907473827895839,
          "isMainstream": true
        }
      ]
    },
    {
      "id": "l2",
      "name": "L2 & 扩容",
      "totalMarketCap": 2628983079,
      "weightedReturnPct": -0.00016477147019168382,
      "weightedAmplitude": 0.03802513906539955,
      "weightedVolatility": 0.019012569532699777,
      "weightedReturnPct7d": 0.03145085623337284,
      "weightedReturnPct30d": -0.10710583047710684,
      "coins": [
        {
          "id": "arbitrum",
          "symbol": "ARB",
          "name": "Arbitrum",
          "marketCap": 507261991,
          "open": 0.07956432787330037,
          "high": 0.080839,
          "low": 0.076448,
          "close": 0.079763,
          "returnPct": 0.002497,
          "amplitude": 0.05743773545416486,
          "volatility": 0.02871886772708243,
          "returnPct7d": 0.033313198580307006,
          "returnPct30d": 0.010910491496691897,
          "isMainstream": true
        },
        {
          "id": "optimism",
          "symbol": "OP",
          "name": "Optimism",
          "marketCap": 232118626,
          "open": 0.10810246798265442,
          "high": 0.108822,
          "low": 0.103818,
          "close": 0.107437,
          "returnPct": -0.0061559,
          "amplitude": 0.048199734150147444,
          "volatility": 0.024099867075073722,
          "returnPct7d": 0.049795631903128565,
          "returnPct30d": 0.15102846471411716,
          "isMainstream": false
        },
        {
          "id": "starknet",
          "symbol": "STRK",
          "name": "Starknet",
          "marketCap": 206652150,
          "open": 0.03143979492418741,
          "high": 0.03192082,
          "low": 0.03049943,
          "close": 0.03140119,
          "returnPct": -0.0012278999999999999,
          "amplitude": 0.04660382177634137,
          "volatility": 0.023301910888170685,
          "returnPct7d": 0.040272782127858286,
          "returnPct30d": 0.00480115536622531,
          "isMainstream": false
        },
        {
          "id": "mantle",
          "symbol": "MNT",
          "name": "Mantle",
          "marketCap": 1448995660,
          "open": 0.43913956044198066,
          "high": 0.443311,
          "low": 0.429886,
          "close": 0.438658,
          "returnPct": -0.0010965999999999999,
          "amplitude": 0.031229209604406893,
          "volatility": 0.015614604802203447,
          "returnPct7d": 0.030798890521598777,
          "returnPct30d": -0.14842078821474852,
          "isMainstream": true
        },
        {
          "id": "conflux-token",
          "symbol": "CFX",
          "name": "Conflux",
          "marketCap": 233954652,
          "open": 0.044842767584761134,
          "high": 0.04554078,
          "low": 0.0437855,
          "close": 0.04486518,
          "returnPct": 0.0004998,
          "amplitude": 0.04008815703828894,
          "volatility": 0.02004407851914447,
          "returnPct7d": 0.020662312052073382,
          "returnPct30d": 0.03564938774413801,
          "isMainstream": false
        }
      ]
    },
    {
      "id": "pow",
      "name": "PoW 老币",
      "totalMarketCap": 9526429982,
      "weightedReturnPct": -0.004905347402125775,
      "weightedAmplitude": 0.04981194657211169,
      "weightedVolatility": 0.024905973286055844,
      "weightedReturnPct7d": 0.12697992750207862,
      "weightedReturnPct30d": 0.11568252696448508,
      "coins": [
        {
          "id": "litecoin",
          "symbol": "LTC",
          "name": "Litecoin",
          "marketCap": 3483502559,
          "open": 45.65154579601272,
          "high": 46.02,
          "low": 43.87,
          "close": 45.03,
          "returnPct": -0.013614999999999999,
          "amplitude": 0.049008434009573776,
          "volatility": 0.024504217004786888,
          "returnPct7d": 0.041847506056213096,
          "returnPct30d": 0.09118874736449362,
          "isMainstream": true
        },
        {
          "id": "bitcoin-cash",
          "symbol": "BCH",
          "name": "Bitcoin Cash",
          "marketCap": 4928800569,
          "open": 245.56117477696966,
          "high": 247.65,
          "low": 234.91,
          "close": 245.77,
          "returnPct": 0.0008504000000000001,
          "amplitude": 0.05423353624792471,
          "volatility": 0.027116768123962354,
          "returnPct7d": 0.21603557165807014,
          "returnPct30d": 0.14593147767359452,
          "isMainstream": true
        },
        {
          "id": "ethereum-classic",
          "symbol": "ETC",
          "name": "Ethereum Classic",
          "marketCap": 1114126854,
          "open": 7.142399278376918,
          "high": 7.25,
          "low": 7.02,
          "close": 7.12,
          "returnPct": -0.0031361,
          "amplitude": 0.03276353276353272,
          "volatility": 0.01638176638176636,
          "returnPct7d": -0.0008138700506851038,
          "returnPct30d": 0.05844766064596864,
          "isMainstream": true
        }
      ]
    },
    {
      "id": "defi",
      "name": "DeFi",
      "totalMarketCap": 5712228627,
      "weightedReturnPct": 0.020951948008075486,
      "weightedAmplitude": 0.06910933937190554,
      "weightedVolatility": 0.03455466968595277,
      "weightedReturnPct7d": 0.055274109761895465,
      "weightedReturnPct30d": 0.35805360633826233,
      "coins": [
        {
          "id": "aave",
          "symbol": "AAVE",
          "name": "Aave",
          "marketCap": 1455622890,
          "open": 88.54472478271542,
          "high": 96.9,
          "low": 88.02,
          "close": 95.88,
          "returnPct": 0.0828426,
          "amplitude": 0.10088616223585567,
          "volatility": 0.050443081117927835,
          "returnPct7d": 0.029367593836010855,
          "returnPct30d": 0.5934986951818624,
          "isMainstream": true
        },
        {
          "id": "uniswap",
          "symbol": "UNI",
          "name": "Uniswap",
          "marketCap": 1981870556,
          "open": 3.1542244706316485,
          "high": 3.21,
          "low": 3.08,
          "close": 3.19,
          "returnPct": 0.011342099999999999,
          "amplitude": 0.04220779220779214,
          "volatility": 0.02110389610389607,
          "returnPct7d": 0.07341746445269817,
          "returnPct30d": 0.3177957929196033,
          "isMainstream": true
        },
        {
          "id": "compound-governance-token",
          "symbol": "COMP",
          "name": "Compound",
          "marketCap": 169148845,
          "open": 16.893249345519397,
          "high": 17.68,
          "low": 16.62,
          "close": 17.49,
          "returnPct": 0.0353248,
          "amplitude": 0.06377858002406733,
          "volatility": 0.031889290012033666,
          "returnPct7d": 0.10039149996732415,
          "returnPct30d": 0.09443020105007115,
          "isMainstream": false
        },
        {
          "id": "curve-dao-token",
          "symbol": "CRV",
          "name": "Curve DAO",
          "marketCap": 326952147,
          "open": 0.21170593433804338,
          "high": 0.21496,
          "low": 0.200732,
          "close": 0.213707,
          "returnPct": 0.0094521,
          "amplitude": 0.07088057708785844,
          "volatility": 0.03544028854392922,
          "returnPct7d": 0.1007640817524707,
          "returnPct30d": 0.18204951320986923,
          "isMainstream": true
        },
        {
          "id": "lido-dao",
          "symbol": "LDO",
          "name": "Lido DAO",
          "marketCap": 236148818,
          "open": 0.2735025148226017,
          "high": 0.282748,
          "low": 0.261791,
          "close": 0.280194,
          "returnPct": 0.0244659,
          "amplitude": 0.08005240821876991,
          "volatility": 0.040026204109384955,
          "returnPct7d": 0.10073293609362166,
          "returnPct30d": 0.10230990700314795,
          "isMainstream": false
        },
        {
          "id": "jupiter-exchange-solana",
          "symbol": "JUP",
          "name": "Jupiter",
          "marketCap": 791127566,
          "open": 0.24495285049645046,
          "high": 0.24861,
          "low": 0.234029,
          "close": 0.238225,
          "returnPct": -0.027465899999999998,
          "amplitude": 0.062304244345786186,
          "volatility": 0.031152122172893093,
          "returnPct7d": 0.09233102179615749,
          "returnPct30d": 0.5619720927120722,
          "isMainstream": true
        },
        {
          "id": "ethena",
          "symbol": "ENA",
          "name": "Ethena",
          "marketCap": 751357805,
          "open": 0.07997902242975395,
          "high": 0.08122,
          "low": 0.074864,
          "close": 0.07857,
          "returnPct": -0.017617400000000002,
          "amplitude": 0.08490061979055352,
          "volatility": 0.04245030989527676,
          "returnPct7d": -0.0012069052950113963,
          "returnPct30d": -0.13001493146530274,
          "isMainstream": true
        },
        {
          "id": "maker",
          "symbol": "MKR",
          "name": "Maker",
          "marketCap": 0,
          "open": 1320.7751732857027,
          "high": 1343.06,
          "low": 1283.22,
          "close": 1293.75,
          "returnPct": -0.0204616,
          "amplitude": 0.0466326896401239,
          "volatility": 0.02331634482006195,
          "returnPct7d": 0.05269689513543801,
          "returnPct30d": 0.0012239798877643926,
          "isMainstream": false
        }
      ]
    },
    {
      "id": "dex-perp",
      "name": "衍生品 DEX",
      "totalMarketCap": 17647771290,
      "weightedReturnPct": 0.011610064316801779,
      "weightedAmplitude": 0.05004874538297882,
      "weightedVolatility": 0.02502437269148941,
      "weightedReturnPct7d": 0.059217647333019756,
      "weightedReturnPct30d": 0.2485106902452173,
      "coins": [
        {
          "id": "hyperliquid",
          "symbol": "HYPE",
          "name": "Hyperliquid",
          "marketCap": 15827757919,
          "open": 70.1857891042334,
          "high": 72.4,
          "low": 68.79,
          "close": 71.14,
          "returnPct": 0.0135955,
          "amplitude": 0.05247855792993161,
          "volatility": 0.026239278964965806,
          "returnPct7d": 0.06379018453563845,
          "returnPct30d": 0.2728885173026075,
          "isMainstream": true
        },
        {
          "id": "dydx-chain",
          "symbol": "DYDX",
          "name": "dYdX",
          "marketCap": 109992346,
          "open": 0.1268316624254146,
          "high": 0.132568,
          "low": 0.125812,
          "close": 0.129675,
          "returnPct": 0.022418200000000003,
          "amplitude": 0.05369917019044279,
          "volatility": 0.026849585095221395,
          "returnPct7d": -0.199284078809108,
          "returnPct30d": -0.018035745009466586,
          "isMainstream": false
        },
        {
          "id": "aster-2",
          "symbol": "ASTER",
          "name": "Aster",
          "marketCap": 1710021025,
          "open": 0.6422752121329827,
          "high": 0.646953,
          "low": 0.629602,
          "close": 0.637929,
          "returnPct": -0.0067669,
          "amplitude": 0.027558679927954577,
          "volatility": 0.013779339963977288,
          "returnPct7d": 0.016894768923574402,
          "returnPct30d": 0.022872326965081922,
          "isMainstream": true
        }
      ]
    },
    {
      "id": "ai",
      "name": "AI",
      "totalMarketCap": 5087861344,
      "weightedReturnPct": 0.0014603499744207066,
      "weightedAmplitude": 0.054492088527795794,
      "weightedVolatility": 0.027246044263897897,
      "weightedReturnPct7d": 0.0019319226564278897,
      "weightedReturnPct30d": 0.04004389314730184,
      "coins": [
        {
          "id": "bittensor",
          "symbol": "TAO",
          "name": "Bittensor",
          "marketCap": 2062441947,
          "open": 213.6432406442346,
          "high": 218,
          "low": 207.46,
          "close": 214.88,
          "returnPct": 0.0057889000000000005,
          "amplitude": 0.05080497445290644,
          "volatility": 0.02540248722645322,
          "returnPct7d": 0.03038608650059259,
          "returnPct30d": 0.10550187431633638,
          "isMainstream": true
        },
        {
          "id": "fetch-ai",
          "symbol": "FET",
          "name": "Artificial Superintelligence Alliance",
          "marketCap": 388022538,
          "open": 0.17582443993321828,
          "high": 0.180358,
          "low": 0.166606,
          "close": 0.17265,
          "returnPct": -0.0180546,
          "amplitude": 0.08254204530449072,
          "volatility": 0.04127102265224536,
          "returnPct7d": -0.024332168676045863,
          "returnPct30d": -0.10782518021844499,
          "isMainstream": true
        },
        {
          "id": "worldcoin-wld",
          "symbol": "WLD",
          "name": "Worldcoin",
          "marketCap": 1446028534,
          "open": 0.40698766985459944,
          "high": 0.427241,
          "low": 0.40356,
          "close": 0.411056,
          "returnPct": 0.0099962,
          "amplitude": 0.058680245812270826,
          "volatility": 0.029340122906135413,
          "returnPct7d": -0.038354471571657014,
          "returnPct30d": 0.007793635407221969,
          "isMainstream": true
        },
        {
          "id": "virtual-protocol",
          "symbol": "VIRTUAL",
          "name": "Virtuals Protocol",
          "marketCap": 361684334,
          "open": 0.5664361229941568,
          "high": 0.57105,
          "low": 0.535969,
          "close": 0.550031,
          "returnPct": -0.028961999999999998,
          "amplitude": 0.06545341241750902,
          "volatility": 0.03272670620875451,
          "returnPct7d": 0.004689747883942518,
          "returnPct30d": 0.026590694309878177,
          "isMainstream": true
        },
        {
          "id": "render-token",
          "symbol": "RENDER",
          "name": "Render",
          "marketCap": 829683991,
          "open": 1.6028656031252675,
          "high": 1.62,
          "low": 1.56,
          "close": 1.6,
          "returnPct": -0.0017878,
          "amplitude": 0.03846153846153855,
          "volatility": 0.019230769230769273,
          "returnPct7d": 0.012494753563401316,
          "returnPct30d": 0.00855461639786697,
          "isMainstream": true
        }
      ]
    },
    {
      "id": "depin",
      "name": "DePIN",
      "totalMarketCap": 754859818,
      "weightedReturnPct": 0.0038418999999999997,
      "weightedAmplitude": 0.05479303003607683,
      "weightedVolatility": 0.027396515018038414,
      "weightedReturnPct7d": 0.07357759789649024,
      "weightedReturnPct30d": 0.09269766989699307,
      "coins": [
        {
          "id": "filecoin",
          "symbol": "FIL",
          "name": "Filecoin",
          "marketCap": 631053679,
          "open": 0.7902399770322398,
          "high": 0.804613,
          "low": 0.762816,
          "close": 0.793276,
          "returnPct": 0.0038418999999999997,
          "amplitude": 0.05479303003607683,
          "volatility": 0.027396515018038414,
          "returnPct7d": 0.07357759789649024,
          "returnPct30d": 0.09269766989699307,
          "isMainstream": true
        },
        {
          "id": "livepeer",
          "symbol": "LPT",
          "name": "Livepeer",
          "marketCap": 80187031,
          "open": 1.6213151584911094,
          "high": 1.65,
          "low": 1.57,
          "close": 1.61,
          "returnPct": -0.006979,
          "amplitude": 0.05095541401273884,
          "volatility": 0.02547770700636942,
          "returnPct7d": 0.018521717792948842,
          "returnPct30d": -0.08289286635560425,
          "isMainstream": false
        },
        {
          "id": "helium",
          "symbol": "HNT",
          "name": "Helium",
          "marketCap": 43619108,
          "open": 0.24066658057109483,
          "high": 0.244521,
          "low": 0.231935,
          "close": 0.239654,
          "returnPct": -0.0042074,
          "amplitude": 0.05426520361308129,
          "volatility": 0.027132601806540646,
          "returnPct7d": -0.0856873101737162,
          "returnPct30d": -0.49993544966521325,
          "isMainstream": false
        }
      ]
    },
    {
      "id": "meme",
      "name": "Memecoin",
      "totalMarketCap": 16810372634,
      "weightedReturnPct": -0.005540285606802923,
      "weightedAmplitude": 0.05619888365148007,
      "weightedVolatility": 0.028099441825740035,
      "weightedReturnPct7d": 0.041825281207138215,
      "weightedReturnPct30d": -0.03479058555518971,
      "coins": [
        {
          "id": "dogecoin",
          "symbol": "DOGE",
          "name": "Dogecoin",
          "marketCap": 11890358340,
          "open": 0.07729840609941141,
          "high": 0.0786,
          "low": 0.074517,
          "close": 0.07673,
          "returnPct": -0.0073533999999999995,
          "amplitude": 0.05479286605740974,
          "volatility": 0.02739643302870487,
          "returnPct7d": 0.03875772141692003,
          "returnPct30d": -0.04939130448900377,
          "isMainstream": true
        },
        {
          "id": "pepe",
          "symbol": "PEPE",
          "name": "Pepe",
          "marketCap": 1146731320,
          "open": 0.0000026974287256523586,
          "high": 0.00000279,
          "low": 0.00000262,
          "close": 0.00000272,
          "returnPct": 0.0083677,
          "amplitude": 0.06488549618320616,
          "volatility": 0.03244274809160308,
          "returnPct7d": 0.1386923584077823,
          "returnPct30d": 0.03031097899141334,
          "isMainstream": true
        },
        {
          "id": "dogwifcoin",
          "symbol": "WIF",
          "name": "dogwifhat",
          "marketCap": 171189191,
          "open": 0.1747998490581432,
          "high": 0.17909,
          "low": 0.168047,
          "close": 0.171393,
          "returnPct": -0.01949,
          "amplitude": 0.0657137586508536,
          "volatility": 0.0328568793254268,
          "returnPct7d": -0.05539510399441941,
          "returnPct30d": 0.14525595364926489,
          "isMainstream": false
        },
        {
          "id": "official-trump",
          "symbol": "TRUMP",
          "name": "Official Trump",
          "marketCap": 400859495,
          "open": 1.7014795421751474,
          "high": 1.72,
          "low": 1.63,
          "close": 1.69,
          "returnPct": -0.0067468,
          "amplitude": 0.05521472392638049,
          "volatility": 0.027607361963190247,
          "returnPct7d": 0.014272880336113599,
          "returnPct30d": 0.08105656607030445,
          "isMainstream": true
        },
        {
          "id": "shiba-inu",
          "symbol": "SHIB",
          "name": "Shiba Inu",
          "marketCap": 2589272809,
          "open": 0.000004358546116098563,
          "high": 0.00000444,
          "low": 0.00000427,
          "close": 0.00000439,
          "returnPct": 0.0072166,
          "amplitude": 0.03981264637002346,
          "volatility": 0.01990632318501173,
          "returnPct7d": 0.02172381302126677,
          "returnPct30d": -0.026270225785580067,
          "isMainstream": true
        },
        {
          "id": "bonk",
          "symbol": "BONK",
          "name": "Bonk",
          "marketCap": 384645778,
          "open": 0.000004727249597480646,
          "high": 0.00000493,
          "low": 0.00000416,
          "close": 0.00000437,
          "returnPct": -0.0755724,
          "amplitude": 0.18509615384615397,
          "volatility": 0.09254807692307698,
          "returnPct7d": 0.011893067382305524,
          "returnPct30d": 0.044383065288701354,
          "isMainstream": true
        },
        {
          "id": "floki",
          "symbol": "FLOKI",
          "name": "FLOKI",
          "marketCap": 227315701,
          "open": 0.000023610335188526622,
          "high": 0.00002403,
          "low": 0.00002273,
          "close": 0.00002354,
          "returnPct": -0.002979,
          "amplitude": 0.05719313682358096,
          "volatility": 0.02859656841179048,
          "returnPct7d": 0.05317130937845173,
          "returnPct30d": 0.022164306530327475,
          "isMainstream": false
        }
      ]
    },
    {
      "id": "privacy",
      "name": "隐私币",
      "totalMarketCap": 14064158609,
      "weightedReturnPct": -0.02018344939328437,
      "weightedAmplitude": 0.049557473573302195,
      "weightedVolatility": 0.024778736786651098,
      "weightedReturnPct7d": 0.07478430096744579,
      "weightedReturnPct30d": 0.1904798787212008,
      "coins": [
        {
          "id": "monero",
          "symbol": "XMR",
          "name": "Monero",
          "marketCap": 6084653538,
          "open": 327.74864737329403,
          "high": 329.57,
          "low": 316.32,
          "close": 324.15,
          "returnPct": -0.0109799,
          "amplitude": 0.041887961557915965,
          "volatility": 0.020943980778957982,
          "returnPct7d": 0.03952901912279818,
          "returnPct30d": 0.10037915953298608,
          "isMainstream": true
        },
        {
          "id": "zcash",
          "symbol": "ZEC",
          "name": "Zcash",
          "marketCap": 7534619216,
          "open": 461.8585897670743,
          "high": 465.73,
          "low": 441.15,
          "close": 448.8,
          "returnPct": -0.028274,
          "amplitude": 0.05571800974725161,
          "volatility": 0.027859004873625803,
          "returnPct7d": 0.10483400814505758,
          "returnPct30d": 0.26808685014744127,
          "isMainstream": true
        },
        {
          "id": "dash",
          "symbol": "DASH",
          "name": "Dash",
          "marketCap": 444885855,
          "open": 35.19809219881917,
          "high": 35.83,
          "low": 34.12,
          "close": 34.88,
          "returnPct": -0.0090372,
          "amplitude": 0.05011723329425566,
          "volatility": 0.02505861664712783,
          "returnPct7d": 0.04804277706265723,
          "returnPct30d": 0.10841991208369306,
          "isMainstream": true
        }
      ]
    },
    {
      "id": "rwa",
      "name": "RWA",
      "totalMarketCap": 1640704777,
      "weightedReturnPct": 0.022184999999999996,
      "weightedAmplitude": 0.04682894610952171,
      "weightedVolatility": 0.023414473054760854,
      "weightedReturnPct7d": 0.05776198437700798,
      "weightedReturnPct30d": 0.051131983450724304,
      "coins": [
        {
          "id": "ondo-finance",
          "symbol": "ONDO",
          "name": "Ondo",
          "marketCap": 1640704777,
          "open": 0.329620372046156,
          "high": 0.339182,
          "low": 0.324009,
          "close": 0.336933,
          "returnPct": 0.022185,
          "amplitude": 0.04682894610952171,
          "volatility": 0.023414473054760854,
          "returnPct7d": 0.05776198437700798,
          "returnPct30d": 0.05113198345072431,
          "isMainstream": true
        }
      ]
    },
    {
      "id": "btc-eco",
      "name": "BTC 生态",
      "totalMarketCap": 388350095,
      "weightedReturnPct": -0.0138485,
      "weightedAmplitude": 0.05324771130380102,
      "weightedVolatility": 0.02662385565190051,
      "weightedReturnPct7d": 0.014318785278323459,
      "weightedReturnPct30d": -0.04213222411509457,
      "coins": [
        {
          "id": "ordinals",
          "symbol": "ORDI",
          "name": "ORDI",
          "marketCap": 72781504,
          "open": 3.225702095969858,
          "high": 3.48,
          "low": 3.22,
          "close": 3.46,
          "returnPct": 0.0726347,
          "amplitude": 0.08074534161490665,
          "volatility": 0.040372670807453326,
          "returnPct7d": -0.18657988824250687,
          "returnPct30d": 0.19025171617877087,
          "isMainstream": false
        },
        {
          "id": "blockstack",
          "symbol": "STX",
          "name": "Stacks",
          "marketCap": 315568591,
          "open": 0.17279799300614562,
          "high": 0.174184,
          "low": 0.165378,
          "close": 0.170405,
          "returnPct": -0.0138485,
          "amplitude": 0.053247711303801015,
          "volatility": 0.026623855651900508,
          "returnPct7d": 0.014318785278323459,
          "returnPct30d": -0.04213222411509457,
          "isMainstream": true
        }
      ]
    },
    {
      "id": "infra",
      "name": "基础设施",
      "totalMarketCap": 6146560622,
      "weightedReturnPct": -0.0039858,
      "weightedAmplitude": 0.04375804375804382,
      "weightedVolatility": 0.02187902187902191,
      "weightedReturnPct7d": 0.07011247927943373,
      "weightedReturnPct30d": 0.09011825003345968,
      "coins": [
        {
          "id": "chainlink",
          "symbol": "LINK",
          "name": "Chainlink",
          "marketCap": 5972718197,
          "open": 8.01193396640329,
          "high": 8.11,
          "low": 7.77,
          "close": 7.98,
          "returnPct": -0.0039858,
          "amplitude": 0.04375804375804382,
          "volatility": 0.02187902187902191,
          "returnPct7d": 0.07011247927943373,
          "returnPct30d": 0.09011825003345968,
          "isMainstream": true
        },
        {
          "id": "ethereum-name-service",
          "symbol": "ENS",
          "name": "Ethereum Name Service",
          "marketCap": 173842425,
          "open": 4.320620982013103,
          "high": 4.38,
          "low": 4.09,
          "close": 4.25,
          "returnPct": -0.016345099999999998,
          "amplitude": 0.07090464547677255,
          "volatility": 0.03545232273838628,
          "returnPct7d": 0.007999700707088194,
          "returnPct30d": -0.05167287911859173,
          "isMainstream": false
        }
      ]
    },
    {
      "id": "other",
      "name": "其他主流",
      "totalMarketCap": 1228271333,
      "weightedReturnPct": -0.0055282,
      "weightedAmplitude": 0.0325021014289717,
      "weightedVolatility": 0.01625105071448585,
      "weightedReturnPct7d": -0.034179802820434556,
      "weightedReturnPct30d": -0.08487315022284432,
      "coins": [
        {
          "id": "pi-network",
          "symbol": "PI",
          "name": "Pi Network",
          "marketCap": 1228271333,
          "open": 0.11339688063552933,
          "high": 0.114235,
          "low": 0.110639,
          "close": 0.11277,
          "returnPct": -0.0055282,
          "amplitude": 0.0325021014289717,
          "volatility": 0.01625105071448585,
          "returnPct7d": -0.034179802820434556,
          "returnPct30d": -0.08487315022284432,
          "isMainstream": true
        }
      ]
    }
  ]
}