{
  "date": "2026-05-31T18",
  "generatedAt": "2026-05-31T18:57:02.586Z",
  "source": "coingecko",
  "sectors": [
    {
      "id": "btc",
      "name": "BTC",
      "totalMarketCap": 1472771280317,
      "weightedReturnPct": -0.0058696,
      "weightedAmplitude": 0.010333733231540965,
      "weightedVolatility": 0.005166866615770482,
      "weightedReturnPct7d": -0.04056894584502385,
      "weightedReturnPct30d": -0.06068831496679949,
      "coins": [
        {
          "id": "bitcoin",
          "symbol": "BTC",
          "name": "Bitcoin",
          "marketCap": 1472771280317,
          "open": 73937.98640500281,
          "high": 74110,
          "low": 73352,
          "close": 73504,
          "returnPct": -0.0058696,
          "amplitude": 0.010333733231540965,
          "volatility": 0.005166866615770482,
          "returnPct7d": -0.04056894584502385,
          "returnPct30d": -0.06068831496679949,
          "isMainstream": true
        }
      ]
    },
    {
      "id": "l1",
      "name": "Layer 1 主流",
      "totalMarketCap": 525566941280,
      "weightedReturnPct": -0.012760348033326074,
      "weightedAmplitude": 0.025711717634434462,
      "weightedVolatility": 0.012855858817217231,
      "weightedReturnPct7d": -0.020132806739674023,
      "weightedReturnPct30d": -0.03496596790192703,
      "coins": [
        {
          "id": "ethereum",
          "symbol": "ETH",
          "name": "Ethereum",
          "marketCap": 241054379276,
          "open": 2025.086217078966,
          "high": 2032.86,
          "low": 1996.8,
          "close": 1997.38,
          "returnPct": -0.0136815,
          "amplitude": 0.018058894230769118,
          "volatility": 0.009029447115384559,
          "returnPct7d": -0.04961248939979282,
          "returnPct30d": -0.13248920653957177,
          "isMainstream": true
        },
        {
          "id": "solana",
          "symbol": "SOL",
          "name": "Solana",
          "marketCap": 47208106379,
          "open": 82.88944478090065,
          "high": 83.15,
          "low": 81.37,
          "close": 81.6,
          "returnPct": -0.0155562,
          "amplitude": 0.021875384048174906,
          "volatility": 0.010937692024087453,
          "returnPct7d": -0.044128361538387596,
          "returnPct30d": -0.030615607411629785,
          "isMainstream": true
        },
        {
          "id": "binancecoin",
          "symbol": "BNB",
          "name": "BNB",
          "marketCap": 95547024729,
          "open": 714.9952170892664,
          "high": 740.7,
          "low": 705.68,
          "close": 708.73,
          "returnPct": -0.0087626,
          "amplitude": 0.04962589275592344,
          "volatility": 0.02481294637796172,
          "returnPct7d": 0.08034070104741575,
          "returnPct30d": 0.1436779607530926,
          "isMainstream": true
        },
        {
          "id": "ripple",
          "symbol": "XRP",
          "name": "XRP",
          "marketCap": 82127184699,
          "open": 1.3544150927871084,
          "high": 1.35,
          "low": 1.32,
          "close": 1.33,
          "returnPct": -0.0180263,
          "amplitude": 0.022727272727272707,
          "volatility": 0.011363636363636354,
          "returnPct7d": -0.017235676944644084,
          "returnPct30d": -0.04870297078451627,
          "isMainstream": true
        },
        {
          "id": "cardano",
          "symbol": "ADA",
          "name": "Cardano",
          "marketCap": 8649184904,
          "open": 0.23723857349134972,
          "high": 0.238238,
          "low": 0.232258,
          "close": 0.232828,
          "returnPct": -0.018591299999999998,
          "amplitude": 0.025747229374230463,
          "volatility": 0.012873614687115231,
          "returnPct7d": -0.04126805743502561,
          "returnPct30d": -0.06716762101751426,
          "isMainstream": true
        },
        {
          "id": "avalanche-2",
          "symbol": "AVAX",
          "name": "Avalanche",
          "marketCap": 3818642830,
          "open": 8.976588670874898,
          "high": 9.05,
          "low": 8.81,
          "close": 8.84,
          "returnPct": -0.0152161,
          "amplitude": 0.02724177071509648,
          "volatility": 0.01362088535754824,
          "returnPct7d": -0.04320476659209114,
          "returnPct30d": -0.035632631659698946,
          "isMainstream": true
        },
        {
          "id": "tron",
          "symbol": "TRX",
          "name": "TRON",
          "marketCap": 33102471229,
          "open": 0.3474064401698915,
          "high": 0.349779,
          "low": 0.345004,
          "close": 0.349117,
          "returnPct": 0.0049238,
          "amplitude": 0.013840419241516022,
          "volatility": 0.006920209620758011,
          "returnPct7d": -0.0477598423041274,
          "returnPct30d": 0.06883465544248969,
          "isMainstream": true
        },
        {
          "id": "the-open-network",
          "symbol": "TON",
          "name": "Toncoin",
          "marketCap": 4929493299,
          "open": 1.8420665876204365,
          "high": 1.91,
          "low": 1.81,
          "close": 1.85,
          "returnPct": 0.0043068,
          "amplitude": 0.055248618784530246,
          "volatility": 0.027624309392265123,
          "returnPct7d": 0.05473330104199853,
          "returnPct30d": 0.39086670853135763,
          "isMainstream": true
        },
        {
          "id": "polkadot",
          "symbol": "DOT",
          "name": "Polkadot",
          "marketCap": 1963856366,
          "open": 1.1930477814607985,
          "high": 1.2,
          "low": 1.16,
          "close": 1.16,
          "returnPct": -0.0277003,
          "amplitude": 0.034482758620689724,
          "volatility": 0.017241379310344862,
          "returnPct7d": -0.07703979581428756,
          "returnPct30d": -0.03728458110483594,
          "isMainstream": true
        },
        {
          "id": "sui",
          "symbol": "SUI",
          "name": "Sui",
          "marketCap": 3514709471,
          "open": 0.9112797018038277,
          "high": 0.921992,
          "low": 0.867688,
          "close": 0.877529,
          "returnPct": -0.0370366,
          "amplitude": 0.06258470786734405,
          "volatility": 0.031292353933672024,
          "returnPct7d": -0.15878812328928826,
          "returnPct30d": -0.05088828778232981,
          "isMainstream": true
        },
        {
          "id": "aptos",
          "symbol": "APT",
          "name": "Aptos",
          "marketCap": 755744479,
          "open": 0.9462108472211416,
          "high": 0.952947,
          "low": 0.914863,
          "close": 0.921753,
          "returnPct": -0.0258482,
          "amplitude": 0.04162809076331642,
          "volatility": 0.02081404538165821,
          "returnPct7d": -0.03055738666038181,
          "returnPct30d": -0.08431657867913568,
          "isMainstream": true
        },
        {
          "id": "near",
          "symbol": "NEAR",
          "name": "NEAR Protocol",
          "marketCap": 2896143619,
          "open": 2.3243599489224507,
          "high": 2.34,
          "low": 2.23,
          "close": 2.23,
          "returnPct": -0.0405961,
          "amplitude": 0.049327354260089606,
          "volatility": 0.024663677130044803,
          "returnPct7d": -0.0807446054587263,
          "returnPct30d": 0.726735384537376,
          "isMainstream": true
        }
      ]
    },
    {
      "id": "l2",
      "name": "L2 & 扩容",
      "totalMarketCap": 3565923296,
      "weightedReturnPct": -0.006841364110397312,
      "weightedAmplitude": 0.05678989187535618,
      "weightedVolatility": 0.02839494593767809,
      "weightedReturnPct7d": -0.001674891971847132,
      "weightedReturnPct30d": -0.008254095841434966,
      "coins": [
        {
          "id": "arbitrum",
          "symbol": "ARB",
          "name": "Arbitrum",
          "marketCap": 632561293,
          "open": 0.1048091969297805,
          "high": 0.104894,
          "low": 0.100522,
          "close": 0.101078,
          "returnPct": -0.0355999,
          "amplitude": 0.043492966713754244,
          "volatility": 0.021746483356877122,
          "returnPct7d": -0.04624490246979915,
          "returnPct30d": -0.1940220056596405,
          "isMainstream": true
        },
        {
          "id": "optimism",
          "symbol": "OP",
          "name": "Optimism",
          "marketCap": 248602079,
          "open": 0.12158974341698572,
          "high": 0.121978,
          "low": 0.115218,
          "close": 0.115498,
          "returnPct": -0.0501008,
          "amplitude": 0.05867138815115691,
          "volatility": 0.029335694075578456,
          "returnPct7d": -0.08785288562756605,
          "returnPct30d": -0.054350651858777424,
          "isMainstream": false
        },
        {
          "id": "starknet",
          "symbol": "STRK",
          "name": "Starknet",
          "marketCap": 233789362,
          "open": 0.037585801771998065,
          "high": 0.03786257,
          "low": 0.03664986,
          "close": 0.03717435,
          "returnPct": -0.010947,
          "amplitude": 0.03308907592007171,
          "volatility": 0.016544537960035854,
          "returnPct7d": -0.057101654195065264,
          "returnPct30d": -0.052259185410889725,
          "isMainstream": false
        },
        {
          "id": "mantle",
          "symbol": "MNT",
          "name": "Mantle",
          "marketCap": 2184549205,
          "open": 0.6606762351146196,
          "high": 0.698247,
          "low": 0.658326,
          "close": 0.661658,
          "returnPct": 0.0014860000000000001,
          "amplitude": 0.06064016915631454,
          "volatility": 0.03032008457815727,
          "returnPct7d": 0.011230866069710967,
          "returnPct30d": 0.045537134387463214,
          "isMainstream": true
        },
        {
          "id": "conflux-token",
          "symbol": "CFX",
          "name": "Conflux",
          "marketCap": 266421357,
          "open": 0.05237969911993367,
          "high": 0.052502,
          "low": 0.050947,
          "close": 0.051308,
          "returnPct": -0.020460199999999998,
          "amplitude": 0.030521914931203042,
          "volatility": 0.015260957465601521,
          "returnPct7d": -0.06616564116899494,
          "returnPct30d": -0.14733485017670256,
          "isMainstream": false
        }
      ]
    },
    {
      "id": "pow",
      "name": "PoW 老币",
      "totalMarketCap": 11240152607,
      "weightedReturnPct": -0.02081215104022685,
      "weightedAmplitude": 0.027993400711989743,
      "weightedVolatility": 0.013996700355994872,
      "weightedReturnPct7d": -0.09705019748671927,
      "weightedReturnPct30d": -0.21231472615360586,
      "coins": [
        {
          "id": "litecoin",
          "symbol": "LTC",
          "name": "Litecoin",
          "marketCap": 3978131078,
          "open": 52.38000037828305,
          "high": 52.65,
          "low": 51.39,
          "close": 51.51,
          "returnPct": -0.0166094,
          "amplitude": 0.024518388791593626,
          "volatility": 0.012259194395796813,
          "returnPct7d": -0.023688426814762475,
          "returnPct30d": -0.07551371129603389,
          "isMainstream": true
        },
        {
          "id": "bitcoin-cash",
          "symbol": "BCH",
          "name": "Bitcoin Cash",
          "marketCap": 5993808314,
          "open": 306.37701193085843,
          "high": 307.03,
          "low": 297.96,
          "close": 299.08,
          "returnPct": -0.0238171,
          "amplitude": 0.030440327560746328,
          "volatility": 0.015220163780373164,
          "returnPct7d": -0.14629559697466096,
          "returnPct30d": -0.33894199287329213,
          "isMainstream": true
        },
        {
          "id": "ethereum-classic",
          "symbol": "ETC",
          "name": "Ethereum Classic",
          "marketCap": 1268213215,
          "open": 8.263564028236496,
          "high": 8.27,
          "low": 8.05,
          "close": 8.1,
          "returnPct": -0.019793400000000003,
          "amplitude": 0.027329192546583725,
          "volatility": 0.013664596273291862,
          "returnPct7d": -0.09442859964297183,
          "returnPct30d": -0.04296844210884917,
          "isMainstream": true
        }
      ]
    },
    {
      "id": "defi",
      "name": "DeFi",
      "totalMarketCap": 5307051064,
      "weightedReturnPct": -0.020239960400115806,
      "weightedAmplitude": 0.04090498907960751,
      "weightedVolatility": 0.020452494539803755,
      "weightedReturnPct7d": -0.09344773898914811,
      "weightedReturnPct30d": -0.09002350194828493,
      "coins": [
        {
          "id": "aave",
          "symbol": "AAVE",
          "name": "Aave",
          "marketCap": 1233436726,
          "open": 83.32831592386269,
          "high": 83.43,
          "low": 80.95,
          "close": 81.24,
          "returnPct": -0.0250613,
          "amplitude": 0.03063619518221139,
          "volatility": 0.015318097591105695,
          "returnPct7d": -0.05326421775498586,
          "returnPct30d": -0.12444218406660701,
          "isMainstream": true
        },
        {
          "id": "uniswap",
          "symbol": "UNI",
          "name": "Uniswap",
          "marketCap": 1891995623,
          "open": 3.070022895365378,
          "high": 3.07,
          "low": 2.96,
          "close": 2.98,
          "returnPct": -0.029323199999999997,
          "amplitude": 0.03716216216216206,
          "volatility": 0.01858108108108103,
          "returnPct7d": -0.12095321829304251,
          "returnPct30d": -0.08122766988892113,
          "isMainstream": true
        },
        {
          "id": "compound-governance-token",
          "symbol": "COMP",
          "name": "Compound",
          "marketCap": 175828522,
          "open": 18.475445635061703,
          "high": 18.72,
          "low": 18.09,
          "close": 18.19,
          "returnPct": -0.015449999999999998,
          "amplitude": 0.03482587064676612,
          "volatility": 0.01741293532338306,
          "returnPct7d": -0.09488061082801501,
          "returnPct30d": -0.24801290677125032,
          "isMainstream": false
        },
        {
          "id": "curve-dao-token",
          "symbol": "CRV",
          "name": "Curve DAO",
          "marketCap": 324420368,
          "open": 0.2164082975452163,
          "high": 0.21668,
          "low": 0.211819,
          "close": 0.213497,
          "returnPct": -0.013452800000000001,
          "amplitude": 0.022948838395044913,
          "volatility": 0.011474419197522456,
          "returnPct7d": -0.05232300178010637,
          "returnPct30d": -0.09205270885170638,
          "isMainstream": true
        },
        {
          "id": "lido-dao",
          "symbol": "LDO",
          "name": "Lido DAO",
          "marketCap": 271618093,
          "open": 0.3248359043422353,
          "high": 0.327871,
          "low": 0.317765,
          "close": 0.319762,
          "returnPct": -0.015619899999999999,
          "amplitude": 0.03180337670920341,
          "volatility": 0.015901688354601706,
          "returnPct7d": -0.0690751827896415,
          "returnPct30d": -0.14558158649878913,
          "isMainstream": false
        },
        {
          "id": "jupiter-exchange-solana",
          "symbol": "JUP",
          "name": "Jupiter",
          "marketCap": 624644352,
          "open": 0.1858891092897514,
          "high": 0.190007,
          "low": 0.181826,
          "close": 0.1881,
          "returnPct": 0.011893599999999999,
          "amplitude": 0.04499356527669329,
          "volatility": 0.022496782638346646,
          "returnPct7d": -0.07263633511157815,
          "returnPct30d": 0.047792345397090784,
          "isMainstream": true
        },
        {
          "id": "ethena",
          "symbol": "ENA",
          "name": "Ethena",
          "marketCap": 785107380,
          "open": 0.08865647900659558,
          "high": 0.092736,
          "low": 0.086651,
          "close": 0.086959,
          "returnPct": -0.019146700000000003,
          "amplitude": 0.07022423284209056,
          "volatility": 0.03511211642104528,
          "returnPct7d": -0.1238448710187907,
          "returnPct30d": -0.16595704339802708,
          "isMainstream": true
        },
        {
          "id": "maker",
          "symbol": "MKR",
          "name": "Maker",
          "marketCap": 0,
          "open": 1513.7987450606736,
          "high": 1549.57,
          "low": 1501.85,
          "close": 1544.27,
          "returnPct": 0.020129,
          "amplitude": 0.03177414522089417,
          "volatility": 0.015887072610447084,
          "returnPct7d": -0.05244742069842463,
          "returnPct30d": -0.18459391367612668,
          "isMainstream": false
        }
      ]
    },
    {
      "id": "dex-perp",
      "name": "衍生品 DEX",
      "totalMarketCap": 17326025674,
      "weightedReturnPct": 0.0056867132611128236,
      "weightedAmplitude": 0.045610186770711936,
      "weightedVolatility": 0.022805093385355968,
      "weightedReturnPct7d": 0.08007235856257285,
      "weightedReturnPct30d": 0.6176248987587696,
      "coins": [
        {
          "id": "hyperliquid",
          "symbol": "HYPE",
          "name": "Hyperliquid",
          "marketCap": 15322852481,
          "open": 68.17287008772803,
          "high": 69.94,
          "low": 67.22,
          "close": 68.88,
          "returnPct": 0.010372600000000001,
          "amplitude": 0.0404641475751264,
          "volatility": 0.0202320737875632,
          "returnPct7d": 0.0881788570085135,
          "returnPct30d": 0.6817043113124626,
          "isMainstream": true
        },
        {
          "id": "dydx-chain",
          "symbol": "DYDX",
          "name": "dYdX",
          "marketCap": 152156395,
          "open": 0.1863025826828933,
          "high": 0.189312,
          "low": 0.179502,
          "close": 0.181219,
          "returnPct": -0.0272867,
          "amplitude": 0.05465120165792037,
          "volatility": 0.027325600828960184,
          "returnPct7d": 0.2533836409312548,
          "returnPct30d": 0.2223968718156292,
          "isMainstream": false
        },
        {
          "id": "aster-2",
          "symbol": "ASTER",
          "name": "Aster",
          "marketCap": 1851016798,
          "open": 0.7424175449577545,
          "high": 0.774791,
          "low": 0.711987,
          "close": 0.717841,
          "returnPct": -0.0331034,
          "amplitude": 0.08820947573480975,
          "volatility": 0.044104737867404875,
          "returnPct7d": 0.012966171326013676,
          "returnPct30d": 0.08717083335521099,
          "isMainstream": true
        }
      ]
    },
    {
      "id": "ai",
      "name": "AI",
      "totalMarketCap": 5653220917,
      "weightedReturnPct": -0.03155154876380961,
      "weightedAmplitude": 0.0781429096326359,
      "weightedVolatility": 0.03907145481631795,
      "weightedReturnPct7d": 0.014120181996398333,
      "weightedReturnPct30d": 0.11508846869793327,
      "coins": [
        {
          "id": "bittensor",
          "symbol": "TAO",
          "name": "Bittensor",
          "marketCap": 2416674168,
          "open": 253.78960971368872,
          "high": 259.66,
          "low": 250.4,
          "close": 251.81,
          "returnPct": -0.0078002,
          "amplitude": 0.0369808306709265,
          "volatility": 0.01849041533546325,
          "returnPct7d": -0.09354513614211876,
          "returnPct30d": -0.07561099368583896,
          "isMainstream": true
        },
        {
          "id": "fetch-ai",
          "symbol": "FET",
          "name": "Artificial Superintelligence Alliance",
          "marketCap": 599979837,
          "open": 0.27158354016363057,
          "high": 0.282083,
          "low": 0.260345,
          "close": 0.26581,
          "returnPct": -0.0212588,
          "amplitude": 0.08349689834642482,
          "volatility": 0.04174844917321241,
          "returnPct7d": 0.25806136359844845,
          "returnPct30d": 0.3233630632693446,
          "isMainstream": true
        },
        {
          "id": "worldcoin-wld",
          "symbol": "WLD",
          "name": "Worldcoin",
          "marketCap": 1118239241,
          "open": 0.3660111513141773,
          "high": 0.377963,
          "low": 0.3181,
          "close": 0.333067,
          "returnPct": -0.0900086,
          "amplitude": 0.18818924866394227,
          "volatility": 0.09409462433197113,
          "returnPct7d": 0.12669259978515496,
          "returnPct30d": 0.39967477185632655,
          "isMainstream": true
        },
        {
          "id": "virtual-protocol",
          "symbol": "VIRTUAL",
          "name": "Virtuals Protocol",
          "marketCap": 461978933,
          "open": 0.7289888709461539,
          "high": 0.733307,
          "low": 0.697767,
          "close": 0.703688,
          "returnPct": -0.0347068,
          "amplitude": 0.05093390773711004,
          "volatility": 0.02546695386855502,
          "returnPct7d": -0.060064226345819954,
          "returnPct30d": -0.010135080266886263,
          "isMainstream": true
        },
        {
          "id": "render-token",
          "symbol": "RENDER",
          "name": "Render",
          "marketCap": 1056348738,
          "open": 2.0997874582783043,
          "high": 2.14,
          "low": 2.01,
          "close": 2.04,
          "returnPct": -0.028473099999999998,
          "amplitude": 0.06467661691542315,
          "volatility": 0.03233830845771157,
          "returnPct7d": 0.0351557933867069,
          "returnPct30d": 0.18657336234160465,
          "isMainstream": true
        }
      ]
    },
    {
      "id": "depin",
      "name": "DePIN",
      "totalMarketCap": 960354945,
      "weightedReturnPct": -0.0550623,
      "weightedAmplitude": 0.0678312480884804,
      "weightedVolatility": 0.0339156240442402,
      "weightedReturnPct7d": -0.0354601642356356,
      "weightedReturnPct30d": -0.009431796156037888,
      "coins": [
        {
          "id": "filecoin",
          "symbol": "FIL",
          "name": "Filecoin",
          "marketCap": 728343396,
          "open": 0.9790190400912145,
          "high": 0.988076,
          "low": 0.925311,
          "close": 0.925112,
          "returnPct": -0.0550623,
          "amplitude": 0.0678312480884804,
          "volatility": 0.0339156240442402,
          "returnPct7d": -0.0354601642356356,
          "returnPct30d": -0.009431796156037888,
          "isMainstream": true
        },
        {
          "id": "livepeer",
          "symbol": "LPT",
          "name": "Livepeer",
          "marketCap": 102466187,
          "open": 2.120147961626969,
          "high": 2.14,
          "low": 2.05,
          "close": 2.06,
          "returnPct": -0.0283697,
          "amplitude": 0.043902439024390505,
          "volatility": 0.021951219512195252,
          "returnPct7d": -0.07541877655262781,
          "returnPct30d": -0.020679099701614218,
          "isMainstream": false
        },
        {
          "id": "helium",
          "symbol": "HNT",
          "name": "Helium",
          "marketCap": 129545362,
          "open": 0.7244808366714264,
          "high": 0.730511,
          "low": 0.707611,
          "close": 0.708798,
          "returnPct": -0.021647,
          "amplitude": 0.03236241381210858,
          "volatility": 0.01618120690605429,
          "returnPct7d": -0.10207550474227203,
          "returnPct30d": -0.22780790777920917,
          "isMainstream": false
        }
      ]
    },
    {
      "id": "meme",
      "name": "Memecoin",
      "totalMarketCap": 21368886277,
      "weightedReturnPct": -0.019474017567312044,
      "weightedAmplitude": 0.02425331696618341,
      "weightedVolatility": 0.012126658483091706,
      "weightedReturnPct7d": -0.03221412409147969,
      "weightedReturnPct30d": -0.10373963607680049,
      "coins": [
        {
          "id": "dogecoin",
          "symbol": "DOGE",
          "name": "Dogecoin",
          "marketCap": 15340876687,
          "open": 0.10138671968114543,
          "high": 0.101388,
          "low": 0.099085,
          "close": 0.099314,
          "returnPct": -0.0204437,
          "amplitude": 0.023242670434475476,
          "volatility": 0.011621335217237738,
          "returnPct7d": -0.028903773175102197,
          "returnPct30d": -0.08822289446172712,
          "isMainstream": true
        },
        {
          "id": "pepe",
          "symbol": "PEPE",
          "name": "Pepe",
          "marketCap": 1417748439,
          "open": 0.0000034425538887374755,
          "high": 0.00000346,
          "low": 0.00000335,
          "close": 0.00000337,
          "returnPct": -0.0210756,
          "amplitude": 0.032835820895522394,
          "volatility": 0.016417910447761197,
          "returnPct7d": -0.06140838302607113,
          "returnPct30d": -0.1547763145613491,
          "isMainstream": true
        },
        {
          "id": "dogwifcoin",
          "symbol": "WIF",
          "name": "dogwifhat",
          "marketCap": 187820370,
          "open": 0.19331007217293206,
          "high": 0.19331,
          "low": 0.185663,
          "close": 0.188015,
          "returnPct": -0.027391600000000002,
          "amplitude": 0.04118752794040814,
          "volatility": 0.02059376397020407,
          "returnPct7d": 0.00004894703087738992,
          "returnPct30d": -0.038545012797793994,
          "isMainstream": false
        },
        {
          "id": "official-trump",
          "symbol": "TRUMP",
          "name": "Official Trump",
          "marketCap": 471561288,
          "open": 2.006882295244052,
          "high": 2.02,
          "low": 1.97,
          "close": 1.99,
          "returnPct": -0.0084122,
          "amplitude": 0.025380710659898442,
          "volatility": 0.012690355329949221,
          "returnPct7d": -0.043464795617729875,
          "returnPct30d": -0.14855527025505352,
          "isMainstream": true
        },
        {
          "id": "shiba-inu",
          "symbol": "SHIB",
          "name": "Shiba Inu",
          "marketCap": 3203618791,
          "open": 0.000005528892988581108,
          "high": 0.00000554,
          "low": 0.00000541,
          "close": 0.00000544,
          "returnPct": -0.0160779,
          "amplitude": 0.02402957486136792,
          "volatility": 0.01201478743068396,
          "returnPct7d": -0.023627263841262833,
          "returnPct30d": -0.14296885808484355,
          "isMainstream": true
        },
        {
          "id": "bonk",
          "symbol": "BONK",
          "name": "Bonk",
          "marketCap": 475621697,
          "open": 0.000005505049636519176,
          "high": 0.00000554,
          "low": 0.00000537,
          "close": 0.00000541,
          "returnPct": -0.0172659,
          "amplitude": 0.03165735567970196,
          "volatility": 0.01582867783985098,
          "returnPct7d": -0.09864762799462032,
          "returnPct30d": -0.14342339653139682,
          "isMainstream": true
        },
        {
          "id": "floki",
          "symbol": "FLOKI",
          "name": "FLOKI",
          "marketCap": 271639005,
          "open": 0.000028436105163062977,
          "high": 0.00002971,
          "low": 0.00002799,
          "close": 0.00002814,
          "returnPct": -0.010412999999999999,
          "amplitude": 0.06145051804215784,
          "volatility": 0.03072525902107892,
          "returnPct7d": -0.03815707551442916,
          "returnPct30d": -0.1386544070068991,
          "isMainstream": false
        }
      ]
    },
    {
      "id": "privacy",
      "name": "隐私币",
      "totalMarketCap": 16390171823,
      "weightedReturnPct": -0.008573654297299529,
      "weightedAmplitude": 0.06327282133405719,
      "weightedVolatility": 0.031636410667028596,
      "weightedReturnPct7d": -0.1380973025505392,
      "weightedReturnPct30d": 0.2139970716575166,
      "coins": [
        {
          "id": "monero",
          "symbol": "XMR",
          "name": "Monero",
          "marketCap": 6816814369,
          "open": 376.04227363811526,
          "high": 381.13,
          "low": 358.59,
          "close": 363.14,
          "returnPct": -0.0343107,
          "amplitude": 0.06285730221143937,
          "volatility": 0.031428651105719685,
          "returnPct7d": -0.07578718199208276,
          "returnPct30d": -0.032993002285412326,
          "isMainstream": true
        },
        {
          "id": "zcash",
          "symbol": "ZEC",
          "name": "Zcash",
          "marketCap": 9075452249,
          "open": 537.6766145376162,
          "high": 559.19,
          "low": 525.21,
          "close": 543.82,
          "returnPct": 0.0114258,
          "amplitude": 0.06469793035166882,
          "volatility": 0.03234896517583441,
          "returnPct7d": -0.18498074885130553,
          "returnPct30d": 0.409615839385533,
          "isMainstream": true
        },
        {
          "id": "dash",
          "symbol": "DASH",
          "name": "Dash",
          "marketCap": 497905205,
          "open": 39.97931083429112,
          "high": 40.52,
          "low": 38.85,
          "close": 39.15,
          "returnPct": -0.020743499999999998,
          "amplitude": 0.04298584298584296,
          "volatility": 0.02149292149292148,
          "returnPct7d": -0.13662723755261977,
          "returnPct30d": 0.029939344304969376,
          "isMainstream": true
        }
      ]
    },
    {
      "id": "rwa",
      "name": "RWA",
      "totalMarketCap": 1739682424,
      "weightedReturnPct": 0.0107922,
      "weightedAmplitude": 0.09502675890875878,
      "weightedVolatility": 0.04751337945437939,
      "weightedReturnPct7d": -0.2043389994078131,
      "weightedReturnPct30d": 0.30926895358170803,
      "coins": [
        {
          "id": "ondo-finance",
          "symbol": "ONDO",
          "name": "Ondo",
          "marketCap": 1739682424,
          "open": 0.35357712495209204,
          "high": 0.385894,
          "low": 0.352406,
          "close": 0.357393,
          "returnPct": 0.0107922,
          "amplitude": 0.09502675890875878,
          "volatility": 0.04751337945437939,
          "returnPct7d": -0.20433899940781314,
          "returnPct30d": 0.30926895358170803,
          "isMainstream": true
        }
      ]
    },
    {
      "id": "btc-eco",
      "name": "BTC 生态",
      "totalMarketCap": 503271857,
      "weightedReturnPct": -0.0136488,
      "weightedAmplitude": 0.03113578433490294,
      "weightedVolatility": 0.01556789216745147,
      "weightedReturnPct7d": -0.02886866964537747,
      "weightedReturnPct30d": 0.04601041704981437,
      "coins": [
        {
          "id": "ordinals",
          "symbol": "ORDI",
          "name": "ORDI",
          "marketCap": 70345195,
          "open": 3.507829035929565,
          "high": 3.56,
          "low": 3.3,
          "close": 3.36,
          "returnPct": -0.0421426,
          "amplitude": 0.07878787878787885,
          "volatility": 0.039393939393939426,
          "returnPct7d": -0.14713667027176017,
          "returnPct30d": -0.24308298351159452,
          "isMainstream": false
        },
        {
          "id": "blockstack",
          "symbol": "STX",
          "name": "Stacks",
          "marketCap": 432926662,
          "open": 0.23761414798299024,
          "high": 0.238677,
          "low": 0.23147,
          "close": 0.234371,
          "returnPct": -0.0136488,
          "amplitude": 0.03113578433490294,
          "volatility": 0.01556789216745147,
          "returnPct7d": -0.02886866964537747,
          "returnPct30d": 0.04601041704981437,
          "isMainstream": true
        }
      ]
    },
    {
      "id": "infra",
      "name": "基础设施",
      "totalMarketCap": 6803189154,
      "weightedReturnPct": -0.0222901,
      "weightedAmplitude": 0.028856825749167477,
      "weightedVolatility": 0.014428412874583739,
      "weightedReturnPct7d": -0.044214456233512126,
      "weightedReturnPct30d": -0.018976512094936632,
      "coins": [
        {
          "id": "chainlink",
          "symbol": "LINK",
          "name": "Chainlink",
          "marketCap": 6568674309,
          "open": 9.235868430911868,
          "high": 9.27,
          "low": 9.01,
          "close": 9.03,
          "returnPct": -0.0222901,
          "amplitude": 0.02885682574916748,
          "volatility": 0.01442841287458374,
          "returnPct7d": -0.04421445623351212,
          "returnPct30d": -0.018976512094936632,
          "isMainstream": true
        },
        {
          "id": "ethereum-name-service",
          "symbol": "ENS",
          "name": "Ethereum Name Service",
          "marketCap": 234514845,
          "open": 6.008883823929343,
          "high": 6.04,
          "low": 5.75,
          "close": 5.8,
          "returnPct": -0.0347625,
          "amplitude": 0.050434782608695716,
          "volatility": 0.025217391304347858,
          "returnPct7d": -0.065962759303115,
          "returnPct30d": -0.0487360028849878,
          "isMainstream": false
        }
      ]
    },
    {
      "id": "other",
      "name": "其他主流",
      "totalMarketCap": 1564789491,
      "weightedReturnPct": 0.0161276,
      "weightedAmplitude": 0.05642021996322377,
      "weightedVolatility": 0.028210109981611886,
      "weightedReturnPct7d": -0.01964229204426816,
      "weightedReturnPct30d": -0.18294537134387506,
      "coins": [
        {
          "id": "pi-network",
          "symbol": "PI",
          "name": "Pi Network",
          "marketCap": 1564789491,
          "open": 0.1446717912199216,
          "high": 0.152246,
          "low": 0.144115,
          "close": 0.147005,
          "returnPct": 0.0161276,
          "amplitude": 0.05642021996322377,
          "volatility": 0.028210109981611886,
          "returnPct7d": -0.01964229204426816,
          "returnPct30d": -0.18294537134387506,
          "isMainstream": true
        }
      ]
    }
  ]
}