{
  "date": "2026-07-17T04",
  "generatedAt": "2026-07-17T04:17:21.061Z",
  "source": "coingecko",
  "sectors": [
    {
      "id": "btc",
      "name": "BTC",
      "totalMarketCap": 1272878920338,
      "weightedReturnPct": -0.016586300000000002,
      "weightedAmplitude": 0.02452651515151505,
      "weightedVolatility": 0.012263257575757525,
      "weightedReturnPct7d": -0.0063968678207236,
      "weightedReturnPct30d": -0.034644617955648986,
      "coins": [
        {
          "id": "bitcoin",
          "symbol": "BTC",
          "name": "Bitcoin",
          "marketCap": 1272878920338,
          "open": 64542.521626452835,
          "high": 64914,
          "low": 63360,
          "close": 63472,
          "returnPct": -0.016586300000000002,
          "amplitude": 0.02452651515151505,
          "volatility": 0.012263257575757525,
          "returnPct7d": -0.0063968678207236,
          "returnPct30d": -0.034644617955648986,
          "isMainstream": true
        }
      ]
    },
    {
      "id": "l1",
      "name": "Layer 1 主流",
      "totalMarketCap": 461982259391,
      "weightedReturnPct": -0.025966160199072514,
      "weightedAmplitude": 0.035852938596307775,
      "weightedVolatility": 0.017926469298153887,
      "weightedReturnPct7d": 0.009562420045635813,
      "weightedReturnPct30d": -0.009438448080010656,
      "coins": [
        {
          "id": "ethereum",
          "symbol": "ETH",
          "name": "Ethereum",
          "marketCap": 223127877495,
          "open": 1915.6135387118834,
          "high": 1923.99,
          "low": 1843.81,
          "close": 1849.64,
          "returnPct": -0.034439899999999996,
          "amplitude": 0.043486042488108945,
          "volatility": 0.021743021244054472,
          "returnPct7d": 0.04255957912167529,
          "returnPct30d": 0.032696285564029204,
          "isMainstream": true
        },
        {
          "id": "solana",
          "symbol": "SOL",
          "name": "Solana",
          "marketCap": 43715431808,
          "open": 76.84838859559264,
          "high": 77.4,
          "low": 74.81,
          "close": 75.04,
          "returnPct": -0.0235319,
          "amplitude": 0.034621039967918765,
          "volatility": 0.017310519983959383,
          "returnPct7d": -0.04894654537307905,
          "returnPct30d": 0.019478654026412755,
          "isMainstream": true
        },
        {
          "id": "binancecoin",
          "symbol": "BNB",
          "name": "BNB",
          "marketCap": 76069453564,
          "open": 580.7154882437263,
          "high": 584.09,
          "low": 569.93,
          "close": 571.25,
          "returnPct": -0.0162997,
          "amplitude": 0.024845156422718784,
          "volatility": 0.012422578211359392,
          "returnPct7d": -0.006199552364499819,
          "returnPct30d": -0.054297653661307066,
          "isMainstream": true
        },
        {
          "id": "ripple",
          "symbol": "XRP",
          "name": "XRP",
          "marketCap": 68146641787,
          "open": 1.1114795667572863,
          "high": 1.12,
          "low": 1.084,
          "close": 1.091,
          "returnPct": -0.018425499999999997,
          "amplitude": 0.03321033210332103,
          "volatility": 0.016605166051660514,
          "returnPct7d": -0.014987361788553083,
          "returnPct30d": -0.10133807674062512,
          "isMainstream": true
        },
        {
          "id": "cardano",
          "symbol": "ADA",
          "name": "Cardano",
          "marketCap": 5959920151,
          "open": 0.1648751485884331,
          "high": 0.164875,
          "low": 0.15941,
          "close": 0.159867,
          "returnPct": -0.0303754,
          "amplitude": 0.034282667335800765,
          "volatility": 0.017141333667900382,
          "returnPct7d": -0.04722045328865062,
          "returnPct30d": -0.07403323680696852,
          "isMainstream": true
        },
        {
          "id": "avalanche-2",
          "symbol": "AVAX",
          "name": "Avalanche",
          "marketCap": 2807633206,
          "open": 6.694626861582616,
          "high": 6.72,
          "low": 6.45,
          "close": 6.5,
          "returnPct": -0.0290721,
          "amplitude": 0.041860465116279055,
          "volatility": 0.020930232558139528,
          "returnPct7d": -0.03996431807410099,
          "returnPct30d": -0.06347525086987638,
          "isMainstream": true
        },
        {
          "id": "tron",
          "symbol": "TRX",
          "name": "TRON",
          "marketCap": 30526911492,
          "open": 0.32382060270383006,
          "high": 0.324501,
          "low": 0.321484,
          "close": 0.321793,
          "returnPct": -0.0062615,
          "amplitude": 0.009384603899416533,
          "volatility": 0.004692301949708266,
          "returnPct7d": -0.027985172656998788,
          "returnPct30d": 0.014997297707343128,
          "isMainstream": true
        },
        {
          "id": "the-open-network",
          "symbol": "GRAM",
          "name": "Gram (prev. Toncoin)",
          "marketCap": 4070486367,
          "open": 1.5676669223331514,
          "high": 1.58,
          "low": 1.49,
          "close": 1.49,
          "returnPct": -0.049543,
          "amplitude": 0.06040268456375841,
          "volatility": 0.030201342281879207,
          "returnPct7d": -0.07815635515018458,
          "returnPct30d": -0.0958729351903401,
          "isMainstream": true
        },
        {
          "id": "polkadot",
          "symbol": "DOT",
          "name": "Polkadot",
          "marketCap": 1453776525,
          "open": 0.8432348200230296,
          "high": 0.870921,
          "low": 0.831203,
          "close": 0.858551,
          "returnPct": 0.0181636,
          "amplitude": 0.04778375438972171,
          "volatility": 0.023891877194860855,
          "returnPct7d": 0.01618794688061822,
          "returnPct30d": -0.16072768732983314,
          "isMainstream": true
        },
        {
          "id": "sui",
          "symbol": "SUI",
          "name": "Sui",
          "marketCap": 3005451161,
          "open": 0.7561910664446599,
          "high": 0.757679,
          "low": 0.734324,
          "close": 0.74159,
          "returnPct": -0.0193087,
          "amplitude": 0.03180476193070092,
          "volatility": 0.01590238096535046,
          "returnPct7d": 0.022804376313282308,
          "returnPct30d": -0.08088177991280246,
          "isMainstream": true
        },
        {
          "id": "aptos",
          "symbol": "APT",
          "name": "Aptos",
          "marketCap": 516235442,
          "open": 0.620532561831258,
          "high": 0.620532,
          "low": 0.601308,
          "close": 0.611174,
          "returnPct": -0.015081500000000001,
          "amplitude": 0.0319703047356763,
          "volatility": 0.01598515236783815,
          "returnPct7d": -0.036843082814540705,
          "returnPct30d": -0.09425286239014317,
          "isMainstream": true
        },
        {
          "id": "near",
          "symbol": "NEAR",
          "name": "NEAR Protocol",
          "marketCap": 2582440393,
          "open": 2.053368712115736,
          "high": 2.08,
          "low": 1.96,
          "close": 1.98,
          "returnPct": -0.0357309,
          "amplitude": 0.061224489795918435,
          "volatility": 0.030612244897959218,
          "returnPct7d": 0.0182437190434128,
          "returnPct30d": -0.15250804585800137,
          "isMainstream": true
        }
      ]
    },
    {
      "id": "l2",
      "name": "L2 & 扩容",
      "totalMarketCap": 2678165115,
      "weightedReturnPct": 0.030977574742157614,
      "weightedAmplitude": 0.060438609519130757,
      "weightedVolatility": 0.030219304759565378,
      "weightedReturnPct7d": 0.008655492392814053,
      "weightedReturnPct30d": -0.1551516647001243,
      "coins": [
        {
          "id": "arbitrum",
          "symbol": "ARB",
          "name": "Arbitrum",
          "marketCap": 571082972,
          "open": 0.08728225905970093,
          "high": 0.090847,
          "low": 0.086034,
          "close": 0.089685,
          "returnPct": 0.027528399999999998,
          "amplitude": 0.055942999279354755,
          "volatility": 0.027971499639677377,
          "returnPct7d": -0.018289886426237422,
          "returnPct30d": 0.013121045366618742,
          "isMainstream": true
        },
        {
          "id": "optimism",
          "symbol": "OP",
          "name": "Optimism",
          "marketCap": 223210443,
          "open": 0.10223841642421887,
          "high": 0.102496,
          "low": 0.097338,
          "close": 0.097794,
          "returnPct": -0.0434711,
          "amplitude": 0.05299061003924477,
          "volatility": 0.026495305019622384,
          "returnPct7d": -0.07250554548357942,
          "returnPct30d": -0.10808386243392602,
          "isMainstream": false
        },
        {
          "id": "starknet",
          "symbol": "STRK",
          "name": "Starknet",
          "marketCap": 191024029,
          "open": 0.02879561699795107,
          "high": 0.02889635,
          "low": 0.02818536,
          "close": 0.02832021,
          "returnPct": -0.016509700000000002,
          "amplitude": 0.02522550714271521,
          "volatility": 0.012612753571357604,
          "returnPct7d": -0.07825201425783233,
          "returnPct30d": -0.20624484542681615,
          "isMainstream": false
        },
        {
          "id": "mantle",
          "symbol": "MNT",
          "name": "Mantle",
          "marketCap": 1456899530,
          "open": 0.4273247613940354,
          "high": 0.451788,
          "low": 0.425332,
          "close": 0.44114,
          "returnPct": 0.0323296,
          "amplitude": 0.062200821946150286,
          "volatility": 0.031100410973075143,
          "returnPct7d": 0.019217680588214024,
          "returnPct30d": -0.22111206717990947,
          "isMainstream": true
        },
        {
          "id": "conflux-token",
          "symbol": "CFX",
          "name": "Conflux",
          "marketCap": 235948141,
          "open": 0.04495958534288475,
          "high": 0.04583478,
          "low": 0.04441913,
          "close": 0.0452353,
          "returnPct": 0.0061325,
          "amplitude": 0.031870277513314615,
          "volatility": 0.015935138756657308,
          "returnPct7d": 0.053255753448136905,
          "returnPct30d": -0.08261576450150265,
          "isMainstream": false
        }
      ]
    },
    {
      "id": "pow",
      "name": "PoW 老币",
      "totalMarketCap": 9078529118,
      "weightedReturnPct": 0.0021514432546862927,
      "weightedAmplitude": 0.02369278669834838,
      "weightedVolatility": 0.01184639334917419,
      "weightedReturnPct7d": -0.03232010202638115,
      "weightedReturnPct30d": 0.010757643706760248,
      "coins": [
        {
          "id": "litecoin",
          "symbol": "LTC",
          "name": "Litecoin",
          "marketCap": 3514588718,
          "open": 45.22353775567734,
          "high": 45.73,
          "low": 44.36,
          "close": 45.4,
          "returnPct": 0.003902,
          "amplitude": 0.030883678990081043,
          "volatility": 0.015441839495040521,
          "returnPct7d": 0.02452163623510868,
          "returnPct30d": -0.005262914087507088,
          "isMainstream": true
        },
        {
          "id": "bitcoin-cash",
          "symbol": "BCH",
          "name": "Bitcoin Cash",
          "marketCap": 4471204058,
          "open": 221.67826458041796,
          "high": 224.35,
          "low": 220.58,
          "close": 222.9,
          "returnPct": 0.0055113,
          "amplitude": 0.017091304742043567,
          "volatility": 0.008545652371021784,
          "returnPct7d": -0.0810368097446843,
          "returnPct30d": 0.04203692551133349,
          "isMainstream": true
        },
        {
          "id": "ethereum-classic",
          "symbol": "ETC",
          "name": "Ethereum Classic",
          "marketCap": 1092736342,
          "open": 7.06164818868724,
          "high": 7.08,
          "low": 6.89,
          "close": 6.94,
          "returnPct": -0.0172266,
          "amplitude": 0.027576197387518153,
          "volatility": 0.013788098693759077,
          "returnPct7d": -0.015804673241332202,
          "returnPct30d": -0.06570213606336706,
          "isMainstream": true
        }
      ]
    },
    {
      "id": "defi",
      "name": "DeFi",
      "totalMarketCap": 5818065070,
      "weightedReturnPct": -0.04150306695114885,
      "weightedAmplitude": 0.06498016421477601,
      "weightedVolatility": 0.032490082107388005,
      "weightedReturnPct7d": 0.008296271339493877,
      "weightedReturnPct30d": 0.04441509535946693,
      "coins": [
        {
          "id": "aave",
          "symbol": "AAVE",
          "name": "Aave",
          "marketCap": 1376717940,
          "open": 96.29139070035372,
          "high": 96.42,
          "low": 90.3,
          "close": 90.7,
          "returnPct": -0.0580674,
          "amplitude": 0.0677740863787375,
          "volatility": 0.03388704318936875,
          "returnPct7d": -0.029176728884332266,
          "returnPct30d": 0.1894045056787259,
          "isMainstream": true
        },
        {
          "id": "uniswap",
          "symbol": "UNI",
          "name": "Uniswap",
          "marketCap": 2222122039,
          "open": 3.6854150478091765,
          "high": 3.73,
          "low": 3.52,
          "close": 3.55,
          "returnPct": -0.0367435,
          "amplitude": 0.05965909090909083,
          "volatility": 0.029829545454545414,
          "returnPct7d": 0.027166814569170104,
          "returnPct30d": 0.00903977689270569,
          "isMainstream": true
        },
        {
          "id": "compound-governance-token",
          "symbol": "COMP",
          "name": "Compound",
          "marketCap": 166278362,
          "open": 17.057362919792112,
          "high": 17.57,
          "low": 17.02,
          "close": 17.2,
          "returnPct": 0.0083622,
          "amplitude": 0.03231492361927146,
          "volatility": 0.01615746180963573,
          "returnPct7d": 0.005222539491311623,
          "returnPct30d": -0.05497662361054473,
          "isMainstream": false
        },
        {
          "id": "curve-dao-token",
          "symbol": "CRV",
          "name": "Curve DAO",
          "marketCap": 326935908,
          "open": 0.21786532133448377,
          "high": 0.222834,
          "low": 0.211255,
          "close": 0.212502,
          "returnPct": -0.0246176,
          "amplitude": 0.054810537028709305,
          "volatility": 0.027405268514354653,
          "returnPct7d": 0.030908975444155374,
          "returnPct30d": -0.12999138866411425,
          "isMainstream": true
        },
        {
          "id": "lido-dao",
          "symbol": "LDO",
          "name": "Lido DAO",
          "marketCap": 308115778,
          "open": 0.3686069486842622,
          "high": 0.379972,
          "low": 0.360194,
          "close": 0.368333,
          "returnPct": -0.0007432,
          "amplitude": 0.054909298877826807,
          "volatility": 0.027454649438913403,
          "returnPct7d": 0.19543088365760578,
          "returnPct30d": 0.2753403725260163,
          "isMainstream": true
        },
        {
          "id": "jupiter-exchange-solana",
          "symbol": "JUP",
          "name": "Jupiter",
          "marketCap": 647688282,
          "open": 0.20641786293613462,
          "high": 0.207452,
          "low": 0.192471,
          "close": 0.195052,
          "returnPct": -0.0550624,
          "amplitude": 0.07783510243101555,
          "volatility": 0.03891755121550777,
          "returnPct7d": -0.08912893083162601,
          "returnPct30d": -0.026656851058746357,
          "isMainstream": true
        },
        {
          "id": "ethena",
          "symbol": "ENA",
          "name": "Ethena",
          "marketCap": 770206761,
          "open": 0.08370964431662602,
          "high": 0.085817,
          "low": 0.079988,
          "close": 0.080554,
          "returnPct": -0.0376975,
          "amplitude": 0.07287343101465216,
          "volatility": 0.03643671550732608,
          "returnPct7d": 0.018301678029242135,
          "returnPct30d": -0.07126911354557865,
          "isMainstream": true
        },
        {
          "id": "maker",
          "symbol": "MKR",
          "name": "Maker",
          "marketCap": 0,
          "open": 1461.4408559620406,
          "high": 1469.55,
          "low": 1387.98,
          "close": 1417.36,
          "returnPct": -0.030162599999999998,
          "amplitude": 0.05876885834089829,
          "volatility": 0.029384429170449144,
          "returnPct7d": 0.0578577139618671,
          "returnPct30d": 0.06382062931894178,
          "isMainstream": false
        }
      ]
    },
    {
      "id": "dex-perp",
      "name": "衍生品 DEX",
      "totalMarketCap": 15134125655,
      "weightedReturnPct": -0.08251881357126364,
      "weightedAmplitude": 0.10664060133206833,
      "weightedVolatility": 0.053320300666034166,
      "weightedReturnPct7d": -0.10962965270747375,
      "weightedReturnPct30d": -0.1830237618633928,
      "coins": [
        {
          "id": "hyperliquid",
          "symbol": "HYPE",
          "name": "Hyperliquid",
          "marketCap": 13361867014,
          "open": 66.04121556734484,
          "high": 66.8,
          "low": 59.82,
          "close": 60.07,
          "returnPct": -0.09041650000000001,
          "amplitude": 0.1166833834837846,
          "volatility": 0.0583416917418923,
          "returnPct7d": -0.12140872368731177,
          "returnPct30d": -0.1959198090409995,
          "isMainstream": true
        },
        {
          "id": "dydx-chain",
          "symbol": "DYDX",
          "name": "dYdX",
          "marketCap": 107737460,
          "open": 0.1213781169828422,
          "high": 0.128068,
          "low": 0.119061,
          "close": 0.126739,
          "returnPct": 0.044166800000000006,
          "amplitude": 0.0756502969066275,
          "volatility": 0.03782514845331375,
          "returnPct7d": -0.0585604345918602,
          "returnPct30d": 0.007436345008416045,
          "isMainstream": false
        },
        {
          "id": "aster-2",
          "symbol": "ASTER",
          "name": "Aster",
          "marketCap": 1664521181,
          "open": 0.6319033071850313,
          "high": 0.631914,
          "low": 0.615887,
          "close": 0.619821,
          "returnPct": -0.0191205,
          "amplitude": 0.02602263077480127,
          "volatility": 0.013011315387400635,
          "returnPct7d": -0.015073703658807159,
          "returnPct30d": -0.07950133790124869,
          "isMainstream": true
        }
      ]
    },
    {
      "id": "ai",
      "name": "AI",
      "totalMarketCap": 4723358579,
      "weightedReturnPct": -0.035862354057848274,
      "weightedAmplitude": 0.057828348293727655,
      "weightedVolatility": 0.028914174146863827,
      "weightedReturnPct7d": -0.040138761945327076,
      "weightedReturnPct30d": -0.268174229759712,
      "coins": [
        {
          "id": "bittensor",
          "symbol": "TAO",
          "name": "Bittensor",
          "marketCap": 1840726164,
          "open": 201.27132539476412,
          "high": 202.2,
          "low": 190.17,
          "close": 191.8,
          "returnPct": -0.0470575,
          "amplitude": 0.06325918914655304,
          "volatility": 0.03162959457327652,
          "returnPct7d": -0.10543875166207575,
          "returnPct30d": -0.25381217936969447,
          "isMainstream": true
        },
        {
          "id": "fetch-ai",
          "symbol": "FET",
          "name": "Artificial Superintelligence Alliance",
          "marketCap": 353621833,
          "open": 0.1598813918168295,
          "high": 0.160643,
          "low": 0.15671,
          "close": 0.157843,
          "returnPct": -0.0127494,
          "amplitude": 0.02509731350902955,
          "volatility": 0.012548656754514775,
          "returnPct7d": -0.02525385579620708,
          "returnPct30d": -0.23627092687412798,
          "isMainstream": true
        },
        {
          "id": "worldcoin-wld",
          "symbol": "WLD",
          "name": "Worldcoin",
          "marketCap": 1351821620,
          "open": 0.40018522153898434,
          "high": 0.40431,
          "low": 0.38028,
          "close": 0.381817,
          "returnPct": -0.0458993,
          "amplitude": 0.06319028084569256,
          "volatility": 0.03159514042284628,
          "returnPct7d": -0.007338310248564431,
          "returnPct30d": -0.4377123314272921,
          "isMainstream": true
        },
        {
          "id": "virtual-protocol",
          "symbol": "VIRTUAL",
          "name": "Virtuals Protocol",
          "marketCap": 411146719,
          "open": 0.6165491797333266,
          "high": 0.662507,
          "low": 0.608694,
          "close": 0.625609,
          "returnPct": 0.014694400000000002,
          "amplitude": 0.08840731139127378,
          "volatility": 0.04420365569563689,
          "returnPct7d": 0.16129467281500695,
          "returnPct30d": -0.012613592132849847,
          "isMainstream": true
        },
        {
          "id": "render-token",
          "symbol": "RENDER",
          "name": "Render",
          "marketCap": 766042243,
          "open": 1.524285838612117,
          "high": 1.52,
          "low": 1.47,
          "close": 1.48,
          "returnPct": -0.0290535,
          "amplitude": 0.03401360544217691,
          "volatility": 0.017006802721088454,
          "returnPct7d": -0.05609517149805181,
          "returnPct30d": -0.15539448686057974,
          "isMainstream": true
        }
      ]
    },
    {
      "id": "depin",
      "name": "DePIN",
      "totalMarketCap": 729920554,
      "weightedReturnPct": -0.0140431,
      "weightedAmplitude": 0.02571971357591707,
      "weightedVolatility": 0.012859856787958535,
      "weightedReturnPct7d": -0.02072315673744627,
      "weightedReturnPct30d": -0.05395121079156109,
      "coins": [
        {
          "id": "filecoin",
          "symbol": "FIL",
          "name": "Filecoin",
          "marketCap": 617429428,
          "open": 0.7833699424386603,
          "high": 0.786128,
          "low": 0.766416,
          "close": 0.772369,
          "returnPct": -0.0140431,
          "amplitude": 0.02571971357591707,
          "volatility": 0.012859856787958535,
          "returnPct7d": -0.02072315673744627,
          "returnPct30d": -0.05395121079156109,
          "isMainstream": true
        },
        {
          "id": "livepeer",
          "symbol": "LPT",
          "name": "Livepeer",
          "marketCap": 74840912,
          "open": 1.534234460694234,
          "high": 1.53,
          "low": 1.5,
          "close": 1.51,
          "returnPct": -0.0157958,
          "amplitude": 0.020000000000000018,
          "volatility": 0.010000000000000009,
          "returnPct7d": -0.04133261471828211,
          "returnPct30d": -0.17443161071389962,
          "isMainstream": false
        },
        {
          "id": "helium",
          "symbol": "HNT",
          "name": "Helium",
          "marketCap": 37650214,
          "open": 0.21080191320847033,
          "high": 0.213323,
          "low": 0.205648,
          "close": 0.207068,
          "returnPct": -0.0177129,
          "amplitude": 0.03732105345055636,
          "volatility": 0.01866052672527818,
          "returnPct7d": -0.08457268464311894,
          "returnPct30d": -0.3216468337334547,
          "isMainstream": false
        }
      ]
    },
    {
      "id": "meme",
      "name": "Memecoin",
      "totalMarketCap": 15815547060,
      "weightedReturnPct": -0.021411780494893593,
      "weightedAmplitude": 0.03140905300947501,
      "weightedVolatility": 0.015704526504737505,
      "weightedReturnPct7d": -0.02307561264791992,
      "weightedReturnPct30d": -0.16627393731768977,
      "coins": [
        {
          "id": "dogecoin",
          "symbol": "DOGE",
          "name": "Dogecoin",
          "marketCap": 11205104018,
          "open": 0.07394346372946939,
          "high": 0.074185,
          "low": 0.071882,
          "close": 0.072235,
          "returnPct": -0.023105,
          "amplitude": 0.032038618847555655,
          "volatility": 0.016019309423777828,
          "returnPct7d": -0.023096983875666544,
          "returnPct30d": -0.17321845391892596,
          "isMainstream": true
        },
        {
          "id": "pepe",
          "symbol": "PEPE",
          "name": "Pepe",
          "marketCap": 1153250168,
          "open": 0.00000276878596011291,
          "high": 0.00000278,
          "low": 0.0000027,
          "close": 0.00000274,
          "returnPct": -0.0103966,
          "amplitude": 0.029629629629629672,
          "volatility": 0.014814814814814836,
          "returnPct7d": 0.03126320057403635,
          "returnPct30d": -0.07908764714832545,
          "isMainstream": true
        },
        {
          "id": "dogwifcoin",
          "symbol": "WIF",
          "name": "dogwifhat",
          "marketCap": 151360255,
          "open": 0.1523525554830822,
          "high": 0.154912,
          "low": 0.149555,
          "close": 0.151521,
          "returnPct": -0.0054581000000000005,
          "amplitude": 0.03581959814115199,
          "volatility": 0.017909799070575994,
          "returnPct7d": -0.0530884582468221,
          "returnPct30d": -0.1334047324004257,
          "isMainstream": false
        },
        {
          "id": "official-trump",
          "symbol": "TRUMP",
          "name": "Official Trump",
          "marketCap": 368120998,
          "open": 1.5753747181222673,
          "high": 1.59,
          "low": 1.54,
          "close": 1.55,
          "returnPct": -0.0161071,
          "amplitude": 0.032467532467532534,
          "volatility": 0.016233766233766267,
          "returnPct7d": -0.03811282000731915,
          "returnPct30d": -0.19290935853976507,
          "isMainstream": true
        },
        {
          "id": "shiba-inu",
          "symbol": "SHIB",
          "name": "Shiba Inu",
          "marketCap": 2437588340,
          "open": 0.000004222942389171478,
          "high": 0.00000423,
          "low": 0.00000411,
          "close": 0.00000414,
          "returnPct": -0.0196409,
          "amplitude": 0.02919708029197099,
          "volatility": 0.014598540145985495,
          "returnPct7d": -0.046414773708631854,
          "returnPct30d": -0.17157775127961405,
          "isMainstream": true
        },
        {
          "id": "bonk",
          "symbol": "BONK",
          "name": "Bonk",
          "marketCap": 291131895,
          "open": 0.0000036298810934298494,
          "high": 0.00000365,
          "low": 0.00000331,
          "close": 0.00000331,
          "returnPct": -0.0881244,
          "amplitude": 0.10271903323262843,
          "volatility": 0.051359516616314216,
          "returnPct7d": -0.1737488592645665,
          "returnPct30d": -0.3120551379990169,
          "isMainstream": false
        },
        {
          "id": "floki",
          "symbol": "FLOKI",
          "name": "FLOKI",
          "marketCap": 208991386,
          "open": 0.00002206014216309629,
          "high": 0.00002219,
          "low": 0.00002154,
          "close": 0.00002165,
          "returnPct": -0.018592,
          "amplitude": 0.03017641597028775,
          "volatility": 0.015088207985143876,
          "returnPct7d": -0.051524439221402416,
          "returnPct30d": -0.18872769032950823,
          "isMainstream": false
        }
      ]
    },
    {
      "id": "privacy",
      "name": "隐私币",
      "totalMarketCap": 15661743737,
      "weightedReturnPct": -0.028487616878330374,
      "weightedAmplitude": 0.05963566403600944,
      "weightedVolatility": 0.02981783201800472,
      "weightedReturnPct7d": 0.06761009120111099,
      "weightedReturnPct30d": 0.009912767964290756,
      "coins": [
        {
          "id": "monero",
          "symbol": "XMR",
          "name": "Monero",
          "marketCap": 6219573137,
          "open": 331.17085288567466,
          "high": 337.89,
          "low": 330.23,
          "close": 331.23,
          "returnPct": 0.0001786,
          "amplitude": 0.023195954334857438,
          "volatility": 0.011597977167428719,
          "returnPct7d": 0.04217330411649594,
          "returnPct30d": -0.042002287680890954,
          "isMainstream": true
        },
        {
          "id": "zcash",
          "symbol": "ZEC",
          "name": "Zcash",
          "marketCap": 9015601584,
          "open": 564.0719608664634,
          "high": 570.29,
          "low": 525.31,
          "close": 536.79,
          "returnPct": -0.0483661,
          "amplitude": 0.08562563058003847,
          "volatility": 0.042812815290019235,
          "returnPct7d": 0.0901484784160059,
          "returnPct30d": 0.05151026856925123,
          "isMainstream": true
        },
        {
          "id": "dash",
          "symbol": "DASH",
          "name": "Dash",
          "marketCap": 426569016,
          "open": 34.33364435253659,
          "high": 34.52,
          "low": 33.14,
          "close": 33.43,
          "returnPct": -0.0263195,
          "amplitude": 0.04164152082076056,
          "volatility": 0.02082076041038028,
          "returnPct7d": -0.03786208362827605,
          "returnPct30d": -0.11231131510856475,
          "isMainstream": true
        }
      ]
    },
    {
      "id": "rwa",
      "name": "RWA",
      "totalMarketCap": 1801928769,
      "weightedReturnPct": 0.018781500000000003,
      "weightedAmplitude": 0.08717506064424452,
      "weightedVolatility": 0.04358753032212226,
      "weightedReturnPct7d": 0.15322446277388538,
      "weightedReturnPct30d": -0.017492022967568584,
      "coins": [
        {
          "id": "ondo-finance",
          "symbol": "ONDO",
          "name": "Ondo",
          "marketCap": 1801928769,
          "open": 0.3633095025773436,
          "high": 0.391707,
          "low": 0.360298,
          "close": 0.370133,
          "returnPct": 0.0187815,
          "amplitude": 0.08717506064424452,
          "volatility": 0.04358753032212226,
          "returnPct7d": 0.15322446277388538,
          "returnPct30d": -0.017492022967568584,
          "isMainstream": true
        }
      ]
    },
    {
      "id": "btc-eco",
      "name": "BTC 生态",
      "totalMarketCap": 380463154,
      "weightedReturnPct": -0.032025700000000004,
      "weightedAmplitude": 0.045945170875764774,
      "weightedVolatility": 0.022972585437882387,
      "weightedReturnPct7d": -0.05265158350988593,
      "weightedReturnPct30d": -0.1653639510533996,
      "coins": [
        {
          "id": "ordinals",
          "symbol": "ORDI",
          "name": "ORDI",
          "marketCap": 76062931,
          "open": 3.6711244461495234,
          "high": 3.75,
          "low": 3.49,
          "close": 3.62,
          "returnPct": -0.013926099999999999,
          "amplitude": 0.0744985673352434,
          "volatility": 0.0372492836676217,
          "returnPct7d": -0.002385708226576224,
          "returnPct30d": 0.05852512764861676,
          "isMainstream": false
        },
        {
          "id": "blockstack",
          "symbol": "STX",
          "name": "Stacks",
          "marketCap": 304400223,
          "open": 0.16970491881860914,
          "high": 0.171421,
          "low": 0.163891,
          "close": 0.16427,
          "returnPct": -0.032025700000000004,
          "amplitude": 0.045945170875764774,
          "volatility": 0.022972585437882387,
          "returnPct7d": -0.05265158350988593,
          "returnPct30d": -0.1653639510533996,
          "isMainstream": true
        }
      ]
    },
    {
      "id": "infra",
      "name": "基础设施",
      "totalMarketCap": 6358732993,
      "weightedReturnPct": -0.0315419,
      "weightedAmplitude": 0.03510895883777243,
      "weightedVolatility": 0.017554479418886215,
      "weightedReturnPct7d": 0.045397123598367,
      "weightedReturnPct30d": -0.008802893844297818,
      "coins": [
        {
          "id": "chainlink",
          "symbol": "LINK",
          "name": "Chainlink",
          "marketCap": 6181891565,
          "open": 8.529021544659495,
          "high": 8.55,
          "low": 8.26,
          "close": 8.26,
          "returnPct": -0.0315419,
          "amplitude": 0.03510895883777243,
          "volatility": 0.017554479418886215,
          "returnPct7d": 0.045397123598367,
          "returnPct30d": -0.008802893844297818,
          "isMainstream": true
        },
        {
          "id": "ethereum-name-service",
          "symbol": "ENS",
          "name": "Ethereum Name Service",
          "marketCap": 176841428,
          "open": 4.341000386056948,
          "high": 4.35,
          "low": 4.22,
          "close": 4.31,
          "returnPct": -0.007141300000000001,
          "amplitude": 0.0308056872037914,
          "volatility": 0.0154028436018957,
          "returnPct7d": 0.037162244391485515,
          "returnPct30d": -0.2085340232660024,
          "isMainstream": false
        }
      ]
    },
    {
      "id": "other",
      "name": "其他主流",
      "totalMarketCap": 849769332,
      "weightedReturnPct": 0.0163174,
      "weightedAmplitude": 0.06371058327169132,
      "weightedVolatility": 0.03185529163584566,
      "weightedReturnPct7d": -0.210204860793501,
      "weightedReturnPct30d": -0.4261175624021138,
      "coins": [
        {
          "id": "pi-network",
          "symbol": "PI",
          "name": "Pi Network",
          "marketCap": 849769332,
          "open": 0.07642199179114714,
          "high": 0.077653,
          "low": 0.073002,
          "close": 0.077669,
          "returnPct": 0.0163174,
          "amplitude": 0.06371058327169132,
          "volatility": 0.03185529163584566,
          "returnPct7d": -0.21020486079350104,
          "returnPct30d": -0.4261175624021138,
          "isMainstream": true
        }
      ]
    }
  ]
}