{
  "date": "2026-07-13T23",
  "generatedAt": "2026-07-13T23:06:37.245Z",
  "source": "coingecko",
  "sectors": [
    {
      "id": "btc",
      "name": "BTC",
      "totalMarketCap": 1241529853718,
      "weightedReturnPct": -0.029158299999999998,
      "weightedAmplitude": 0.03849698459150508,
      "weightedVolatility": 0.01924849229575254,
      "weightedReturnPct7d": -0.03833526216828742,
      "weightedReturnPct30d": -0.03950284323979473,
      "coins": [
        {
          "id": "bitcoin",
          "symbol": "BTC",
          "name": "Bitcoin",
          "marketCap": 1241529853718,
          "open": 63763.2273108994,
          "high": 64230,
          "low": 61849,
          "close": 61904,
          "returnPct": -0.0291583,
          "amplitude": 0.03849698459150508,
          "volatility": 0.01924849229575254,
          "returnPct7d": -0.03833526216828742,
          "returnPct30d": -0.03950284323979473,
          "isMainstream": true
        }
      ]
    },
    {
      "id": "l1",
      "name": "Layer 1 主流",
      "totalMarketCap": 448432883135,
      "weightedReturnPct": -0.023109672935220135,
      "weightedAmplitude": 0.04220295909754731,
      "weightedVolatility": 0.021101479548773654,
      "weightedReturnPct7d": -0.049576802924458915,
      "weightedReturnPct30d": -0.00008267662549882151,
      "coins": [
        {
          "id": "ethereum",
          "symbol": "ETH",
          "name": "Ethereum",
          "marketCap": 212094511033,
          "open": 1801.4666879185568,
          "high": 1837.21,
          "low": 1753.21,
          "close": 1757.51,
          "returnPct": -0.0244005,
          "amplitude": 0.047912115491013596,
          "volatility": 0.023956057745506798,
          "returnPct7d": -0.030857038083420763,
          "returnPct30d": 0.04250993630424922,
          "isMainstream": true
        },
        {
          "id": "solana",
          "symbol": "SOL",
          "name": "Solana",
          "marketCap": 43306588089,
          "open": 76.67431794854244,
          "high": 77.96,
          "low": 74.2,
          "close": 74.38,
          "returnPct": -0.029922900000000002,
          "amplitude": 0.050673854447439215,
          "volatility": 0.025336927223719607,
          "returnPct7d": -0.1010328836864431,
          "returnPct30d": 0.07289695680289737,
          "isMainstream": true
        },
        {
          "id": "binancecoin",
          "symbol": "BNB",
          "name": "BNB",
          "marketCap": 76108221424,
          "open": 573.3427502825693,
          "high": 578.97,
          "low": 562.25,
          "close": 564.68,
          "returnPct": -0.0151092,
          "amplitude": 0.02973766118274801,
          "volatility": 0.014868830591374005,
          "returnPct7d": -0.04109539547539264,
          "returnPct30d": -0.0725078352375273,
          "isMainstream": true
        },
        {
          "id": "ripple",
          "symbol": "XRP",
          "name": "XRP",
          "marketCap": 66024517800,
          "open": 1.0844514794144535,
          "high": 1.098,
          "low": 1.056,
          "close": 1.057,
          "returnPct": -0.025313699999999998,
          "amplitude": 0.03977272727272729,
          "volatility": 0.019886363636363646,
          "returnPct7d": -0.08336897732712979,
          "returnPct30d": -0.08380466860361198,
          "isMainstream": true
        },
        {
          "id": "cardano",
          "symbol": "ADA",
          "name": "Cardano",
          "marketCap": 5818252236,
          "open": 0.1616908503676944,
          "high": 0.164024,
          "low": 0.155859,
          "close": 0.15608,
          "returnPct": -0.0347011,
          "amplitude": 0.05238709346268111,
          "volatility": 0.026193546731340556,
          "returnPct7d": -0.15935802374967456,
          "returnPct30d": -0.09186844008012486,
          "isMainstream": true
        },
        {
          "id": "avalanche-2",
          "symbol": "AVAX",
          "name": "Avalanche",
          "marketCap": 2755891671,
          "open": 6.387261038348394,
          "high": 6.66,
          "low": 6.37,
          "close": 6.38,
          "returnPct": -0.0011368,
          "amplitude": 0.04552590266875978,
          "volatility": 0.02276295133437989,
          "returnPct7d": -0.0887565979264256,
          "returnPct30d": -0.050982604390628655,
          "isMainstream": true
        },
        {
          "id": "tron",
          "symbol": "TRX",
          "name": "TRON",
          "marketCap": 30747516744,
          "open": 0.3312007460155639,
          "high": 0.331815,
          "low": 0.32409,
          "close": 0.324126,
          "returnPct": -0.0213609,
          "amplitude": 0.023835971489401198,
          "volatility": 0.011917985744700599,
          "returnPct7d": -0.015287020756584724,
          "returnPct30d": 0.02239210700565775,
          "isMainstream": true
        },
        {
          "id": "the-open-network",
          "symbol": "GRAM",
          "name": "Gram (prev. Toncoin)",
          "marketCap": 4333567080,
          "open": 1.6154735953888897,
          "high": 1.64,
          "low": 1.58,
          "close": 1.59,
          "returnPct": -0.0157685,
          "amplitude": 0.03797468354430378,
          "volatility": 0.01898734177215189,
          "returnPct7d": -0.11433496752248154,
          "returnPct30d": -0.09000805771666938,
          "isMainstream": true
        },
        {
          "id": "polkadot",
          "symbol": "DOT",
          "name": "Polkadot",
          "marketCap": 1404290383,
          "open": 0.8451253992755727,
          "high": 0.854147,
          "low": 0.826847,
          "close": 0.829461,
          "returnPct": -0.018535,
          "amplitude": 0.03301699105154876,
          "volatility": 0.01650849552577438,
          "returnPct7d": -0.07449252109086622,
          "returnPct30d": -0.15588626187632362,
          "isMainstream": true
        },
        {
          "id": "sui",
          "symbol": "SUI",
          "name": "Sui",
          "marketCap": 2891016482,
          "open": 0.7355156047013786,
          "high": 0.744795,
          "low": 0.70998,
          "close": 0.713485,
          "returnPct": -0.0299526,
          "amplitude": 0.04903659258007265,
          "volatility": 0.024518296290036323,
          "returnPct7d": -0.05943426761416653,
          "returnPct30d": -0.07497567281536277,
          "isMainstream": true
        },
        {
          "id": "aptos",
          "symbol": "APT",
          "name": "Aptos",
          "marketCap": 494695638,
          "open": 0.6075619022849512,
          "high": 0.61862,
          "low": 0.581316,
          "close": 0.585883,
          "returnPct": -0.0356818,
          "amplitude": 0.06417163814517379,
          "volatility": 0.032085819072586896,
          "returnPct7d": -0.0817714006074932,
          "returnPct30d": -0.13094512472002112,
          "isMainstream": true
        },
        {
          "id": "near",
          "symbol": "NEAR",
          "name": "NEAR Protocol",
          "marketCap": 2453814555,
          "open": 1.8980231335879898,
          "high": 1.96,
          "low": 1.86,
          "close": 1.89,
          "returnPct": -0.0042271,
          "amplitude": 0.053763440860215006,
          "volatility": 0.026881720430107503,
          "returnPct7d": -0.09193251617062251,
          "returnPct30d": -0.11471865742055481,
          "isMainstream": true
        }
      ]
    },
    {
      "id": "l2",
      "name": "L2 & 扩容",
      "totalMarketCap": 2567826084,
      "weightedReturnPct": -0.009481248013221307,
      "weightedAmplitude": 0.03560707381921111,
      "weightedVolatility": 0.017803536909605556,
      "weightedReturnPct7d": -0.011491754222255495,
      "weightedReturnPct30d": -0.1640033370421109,
      "coins": [
        {
          "id": "arbitrum",
          "symbol": "ARB",
          "name": "Arbitrum",
          "marketCap": 566828843,
          "open": 0.09281655269504432,
          "high": 0.094262,
          "low": 0.088542,
          "close": 0.089084,
          "returnPct": -0.040214299999999994,
          "amplitude": 0.06460210973323388,
          "volatility": 0.03230105486661694,
          "returnPct7d": 0.09797045803193466,
          "returnPct30d": 0.04136147703548092,
          "isMainstream": true
        },
        {
          "id": "optimism",
          "symbol": "OP",
          "name": "Optimism",
          "marketCap": 210167813,
          "open": 0.09992174697792496,
          "high": 0.102427,
          "low": 0.097296,
          "close": 0.097313,
          "returnPct": -0.026107900000000003,
          "amplitude": 0.052735980924190295,
          "volatility": 0.026367990462095148,
          "returnPct7d": -0.10122608055775706,
          "returnPct30d": -0.09481007133198836,
          "isMainstream": false
        },
        {
          "id": "starknet",
          "symbol": "STRK",
          "name": "Starknet",
          "marketCap": 188437453,
          "open": 0.029768508684732208,
          "high": 0.03033757,
          "low": 0.02847626,
          "close": 0.02863195,
          "returnPct": -0.0381799,
          "amplitude": 0.06536356951369315,
          "volatility": 0.03268178475684658,
          "returnPct7d": -0.09768917851414444,
          "returnPct30d": -0.18052593298426875,
          "isMainstream": false
        },
        {
          "id": "mantle",
          "symbol": "MNT",
          "name": "Mantle",
          "marketCap": 1382060037,
          "open": 0.41720789286741794,
          "high": 0.426058,
          "low": 0.416188,
          "close": 0.418511,
          "returnPct": 0.0031234,
          "amplitude": 0.02371524407239023,
          "volatility": 0.011857622036195115,
          "returnPct7d": -0.05638585249814901,
          "returnPct30d": -0.24823028582878756,
          "isMainstream": true
        },
        {
          "id": "conflux-token",
          "symbol": "CFX",
          "name": "Conflux",
          "marketCap": 220331938,
          "open": 0.04421714173764963,
          "high": 0.04489221,
          "low": 0.0420693,
          "close": 0.042251,
          "returnPct": -0.0444656,
          "amplitude": 0.06710142550505971,
          "volatility": 0.033550712752529854,
          "returnPct7d": -0.06782076293509039,
          "returnPct30d": -0.06876611000124469,
          "isMainstream": false
        }
      ]
    },
    {
      "id": "pow",
      "name": "PoW 老币",
      "totalMarketCap": 9108346901,
      "weightedReturnPct": -0.021426008567847127,
      "weightedAmplitude": 0.03926759157530407,
      "weightedVolatility": 0.019633795787652036,
      "weightedReturnPct7d": -0.04755728285081286,
      "weightedReturnPct30d": 0.048309872983674326,
      "coins": [
        {
          "id": "litecoin",
          "symbol": "LTC",
          "name": "Litecoin",
          "marketCap": 3346531580,
          "open": 44.11217240974854,
          "high": 44.41,
          "low": 42.93,
          "close": 43.25,
          "returnPct": -0.019545,
          "amplitude": 0.03447472629862558,
          "volatility": 0.01723736314931279,
          "returnPct7d": -0.04779601439957203,
          "returnPct30d": -0.02215266144689624,
          "isMainstream": true
        },
        {
          "id": "bitcoin-cash",
          "symbol": "BCH",
          "name": "Bitcoin Cash",
          "marketCap": 4690779682,
          "open": 240.52037562936678,
          "high": 243.81,
          "low": 233.62,
          "close": 233.85,
          "returnPct": -0.0277331,
          "amplitude": 0.04361784093827592,
          "volatility": 0.02180892046913796,
          "returnPct7d": -0.047834211135574456,
          "returnPct30d": 0.12050748054404387,
          "isMainstream": true
        },
        {
          "id": "ethereum-classic",
          "symbol": "ETC",
          "name": "Ethereum Classic",
          "marketCap": 1071035639,
          "open": 6.837814634442831,
          "high": 7.06,
          "low": 6.82,
          "close": 6.84,
          "returnPct": 0.0003196,
          "amplitude": 0.035190615835777095,
          "volatility": 0.017595307917888547,
          "returnPct7d": -0.0455984944013879,
          "returnPct30d": -0.04772612265367469,
          "isMainstream": true
        }
      ]
    },
    {
      "id": "defi",
      "name": "DeFi",
      "totalMarketCap": 5769960159,
      "weightedReturnPct": -0.02229239795805874,
      "weightedAmplitude": 0.06058934527894885,
      "weightedVolatility": 0.030294672639474426,
      "weightedReturnPct7d": 0.008897980071973812,
      "weightedReturnPct30d": 0.25881178850341596,
      "coins": [
        {
          "id": "aave",
          "symbol": "AAVE",
          "name": "Aave",
          "marketCap": 1423821941,
          "open": 97.49936626970917,
          "high": 97.58,
          "low": 93.51,
          "close": 93.81,
          "returnPct": -0.0378399,
          "amplitude": 0.04352475671051215,
          "volatility": 0.021762378355256073,
          "returnPct7d": -0.017862689682640792,
          "returnPct30d": 0.39484562476212526,
          "isMainstream": true
        },
        {
          "id": "uniswap",
          "symbol": "UNI",
          "name": "Uniswap",
          "marketCap": 2174655642,
          "open": 3.6139425490520423,
          "high": 3.64,
          "low": 3.45,
          "close": 3.5,
          "returnPct": -0.0315286,
          "amplitude": 0.05507246376811592,
          "volatility": 0.02753623188405796,
          "returnPct7d": 0.08758279855984108,
          "returnPct30d": 0.36671052899358725,
          "isMainstream": true
        },
        {
          "id": "compound-governance-token",
          "symbol": "COMP",
          "name": "Compound",
          "marketCap": 159089878,
          "open": 16.955612554982128,
          "high": 17.12,
          "low": 16.4,
          "close": 16.46,
          "returnPct": -0.02923,
          "amplitude": 0.043902439024390505,
          "volatility": 0.021951219512195252,
          "returnPct7d": -0.05958678099803108,
          "returnPct30d": -0.06761032807218464,
          "isMainstream": false
        },
        {
          "id": "curve-dao-token",
          "symbol": "CRV",
          "name": "Curve DAO",
          "marketCap": 324991498,
          "open": 0.20761287775225318,
          "high": 0.219854,
          "low": 0.201113,
          "close": 0.211588,
          "returnPct": 0.0191468,
          "amplitude": 0.09318641758613322,
          "volatility": 0.04659320879306661,
          "returnPct7d": -0.012305911233537564,
          "returnPct30d": -0.11216882275595014,
          "isMainstream": true
        },
        {
          "id": "lido-dao",
          "symbol": "LDO",
          "name": "Lido DAO",
          "marketCap": 261285539,
          "open": 0.3082628946517114,
          "high": 0.31984,
          "low": 0.295973,
          "close": 0.312459,
          "returnPct": 0.0136121,
          "amplitude": 0.08063911235146448,
          "volatility": 0.04031955617573224,
          "returnPct7d": 0.1050902280610408,
          "returnPct30d": 0.181943300734114,
          "isMainstream": false
        },
        {
          "id": "jupiter-exchange-solana",
          "symbol": "JUP",
          "name": "Jupiter",
          "marketCap": 682443556,
          "open": 0.20062998016815872,
          "high": 0.218136,
          "low": 0.197202,
          "close": 0.205528,
          "returnPct": 0.024413200000000003,
          "amplitude": 0.10615510998874256,
          "volatility": 0.05307755499437128,
          "returnPct7d": -0.1421623235021839,
          "returnPct30d": 0.17559797861716767,
          "isMainstream": true
        },
        {
          "id": "ethena",
          "symbol": "ENA",
          "name": "Ethena",
          "marketCap": 743672105,
          "open": 0.07990950718002222,
          "high": 0.081448,
          "low": 0.077324,
          "close": 0.077793,
          "returnPct": -0.026486299999999997,
          "amplitude": 0.05333402307175006,
          "volatility": 0.02666701153587503,
          "returnPct7d": -0.022068275642990905,
          "returnPct30d": -0.07867067313332964,
          "isMainstream": true
        },
        {
          "id": "maker",
          "symbol": "MKR",
          "name": "Maker",
          "marketCap": 0,
          "open": 1390.9358208858412,
          "high": 1430.71,
          "low": 1349.37,
          "close": 1393.87,
          "returnPct": 0.0021095,
          "amplitude": 0.06027998251035682,
          "volatility": 0.03013999125517841,
          "returnPct7d": 0.062093518892613525,
          "returnPct30d": 0.06879339966196006,
          "isMainstream": false
        }
      ]
    },
    {
      "id": "dex-perp",
      "name": "衍生品 DEX",
      "totalMarketCap": 15817609484,
      "weightedReturnPct": -0.052572697466237384,
      "weightedAmplitude": 0.07759672030896574,
      "weightedVolatility": 0.03879836015448287,
      "weightedReturnPct7d": -0.10734638021295495,
      "weightedReturnPct30d": 0.03514481253066858,
      "coins": [
        {
          "id": "hyperliquid",
          "symbol": "HYPE",
          "name": "Hyperliquid",
          "marketCap": 14037842535,
          "open": 67.11656352985267,
          "high": 67.96,
          "low": 62.67,
          "close": 63.11,
          "returnPct": -0.0596956,
          "amplitude": 0.08441040370193065,
          "volatility": 0.042205201850965324,
          "returnPct7d": -0.11730091356481016,
          "returnPct30d": 0.041845695571568295,
          "isMainstream": true
        },
        {
          "id": "dydx-chain",
          "symbol": "DYDX",
          "name": "dYdX",
          "marketCap": 102242473,
          "open": 0.13110119327492287,
          "high": 0.131595,
          "low": 0.120483,
          "close": 0.120593,
          "returnPct": -0.08015330000000001,
          "amplitude": 0.0922287791638654,
          "volatility": 0.0461143895819327,
          "returnPct7d": -0.06580801893915246,
          "returnPct30d": -0.019251086403741107,
          "isMainstream": false
        },
        {
          "id": "aster-2",
          "symbol": "ASTER",
          "name": "Aster",
          "marketCap": 1677524476,
          "open": 0.6210153370331125,
          "high": 0.627666,
          "low": 0.61501,
          "close": 0.625383,
          "returnPct": 0.0070331,
          "amplitude": 0.020578527178419792,
          "volatility": 0.010289263589209896,
          "returnPct7d": -0.024044959755618447,
          "returnPct30d": -0.02092944588963127,
          "isMainstream": true
        }
      ]
    },
    {
      "id": "ai",
      "name": "AI",
      "totalMarketCap": 4758873190,
      "weightedReturnPct": -0.05039467901143594,
      "weightedAmplitude": 0.07953514170626898,
      "weightedVolatility": 0.03976757085313449,
      "weightedReturnPct7d": -0.0751952337663726,
      "weightedReturnPct30d": -0.22109527676814714,
      "coins": [
        {
          "id": "bittensor",
          "symbol": "TAO",
          "name": "Bittensor",
          "marketCap": 1912687760,
          "open": 209.54702644443103,
          "high": 212.59,
          "low": 198.16,
          "close": 199.32,
          "returnPct": -0.0488054,
          "amplitude": 0.07281994348001608,
          "volatility": 0.03640997174000804,
          "returnPct7d": -0.08349530201444728,
          "returnPct30d": -0.2427961778176985,
          "isMainstream": true
        },
        {
          "id": "fetch-ai",
          "symbol": "FET",
          "name": "Artificial Superintelligence Alliance",
          "marketCap": 350346292,
          "open": 0.1578288009171931,
          "high": 0.160837,
          "low": 0.155891,
          "close": 0.156357,
          "returnPct": -0.0093253,
          "amplitude": 0.031727296636752556,
          "volatility": 0.015863648318376278,
          "returnPct7d": -0.09347784414745754,
          "returnPct30d": -0.2479966770034953,
          "isMainstream": true
        },
        {
          "id": "worldcoin-wld",
          "symbol": "WLD",
          "name": "Worldcoin",
          "marketCap": 1370465998,
          "open": 0.41810123905033614,
          "high": 0.431219,
          "low": 0.385924,
          "close": 0.388049,
          "returnPct": -0.0718779,
          "amplitude": 0.11736766824556133,
          "volatility": 0.058683834122780665,
          "returnPct7d": -0.06613847402685641,
          "returnPct30d": -0.23101768741484943,
          "isMainstream": true
        },
        {
          "id": "virtual-protocol",
          "symbol": "VIRTUAL",
          "name": "Virtuals Protocol",
          "marketCap": 357891754,
          "open": 0.5745017913919224,
          "high": 0.581498,
          "low": 0.542844,
          "close": 0.54415,
          "returnPct": -0.0528315,
          "amplitude": 0.07120646078799786,
          "volatility": 0.03560323039399893,
          "returnPct7d": -0.021513863519032887,
          "returnPct30d": -0.15538965382075523,
          "isMainstream": true
        },
        {
          "id": "render-token",
          "symbol": "RENDER",
          "name": "Render",
          "marketCap": 767481386,
          "open": 1.5314647187263264,
          "high": 1.55,
          "low": 1.47,
          "close": 1.48,
          "returnPct": -0.0336049,
          "amplitude": 0.054421768707483054,
          "volatility": 0.027210884353741527,
          "returnPct7d": -0.08736936267697945,
          "returnPct30d": -0.16765465898396,
          "isMainstream": true
        }
      ]
    },
    {
      "id": "depin",
      "name": "DePIN",
      "totalMarketCap": 703656093,
      "weightedReturnPct": -0.0366986,
      "weightedAmplitude": 0.061018715391180756,
      "weightedVolatility": 0.030509357695590378,
      "weightedReturnPct7d": -0.07420523168480156,
      "weightedReturnPct30d": -0.06010846350790103,
      "coins": [
        {
          "id": "filecoin",
          "symbol": "FIL",
          "name": "Filecoin",
          "marketCap": 591222179,
          "open": 0.7692898608888142,
          "high": 0.781957,
          "low": 0.736987,
          "close": 0.741058,
          "returnPct": -0.0366986,
          "amplitude": 0.061018715391180756,
          "volatility": 0.030509357695590378,
          "returnPct7d": -0.07420523168480156,
          "returnPct30d": -0.06010846350790102,
          "isMainstream": true
        },
        {
          "id": "livepeer",
          "symbol": "LPT",
          "name": "Livepeer",
          "marketCap": 74485939,
          "open": 1.5318657174682018,
          "high": 1.55,
          "low": 1.49,
          "close": 1.5,
          "returnPct": -0.020801899999999998,
          "amplitude": 0.04026845637583887,
          "volatility": 0.020134228187919434,
          "returnPct7d": -0.07528728398370442,
          "returnPct30d": -0.17558968728031657,
          "isMainstream": false
        },
        {
          "id": "helium",
          "symbol": "HNT",
          "name": "Helium",
          "marketCap": 37947975,
          "open": 0.2189511015817595,
          "high": 0.220713,
          "low": 0.207905,
          "close": 0.208647,
          "returnPct": -0.047061200000000004,
          "amplitude": 0.06160506000336685,
          "volatility": 0.030802530001683426,
          "returnPct7d": -0.1384143168514333,
          "returnPct30d": -0.31057121540269333,
          "isMainstream": false
        }
      ]
    },
    {
      "id": "meme",
      "name": "Memecoin",
      "totalMarketCap": 15646522987,
      "weightedReturnPct": -0.021272633589500902,
      "weightedAmplitude": 0.04305252436863882,
      "weightedVolatility": 0.02152626218431941,
      "weightedReturnPct7d": -0.0768129974761469,
      "weightedReturnPct30d": -0.18095368978489323,
      "coins": [
        {
          "id": "dogecoin",
          "symbol": "DOGE",
          "name": "Dogecoin",
          "marketCap": 11043277843,
          "open": 0.07258095664271012,
          "high": 0.073832,
          "low": 0.070982,
          "close": 0.071221,
          "returnPct": -0.0187371,
          "amplitude": 0.04015102420331895,
          "volatility": 0.020075512101659476,
          "returnPct7d": -0.07987273982509942,
          "returnPct30d": -0.1892776739652357,
          "isMainstream": true
        },
        {
          "id": "pepe",
          "symbol": "PEPE",
          "name": "Pepe",
          "marketCap": 1131085170,
          "open": 0.0000027584617094751214,
          "high": 0.0000028,
          "low": 0.00000267,
          "close": 0.00000269,
          "returnPct": -0.0248188,
          "amplitude": 0.048689138576779145,
          "volatility": 0.024344569288389573,
          "returnPct7d": -0.019528124524839516,
          "returnPct30d": -0.06279615823715028,
          "isMainstream": true
        },
        {
          "id": "dogwifcoin",
          "symbol": "WIF",
          "name": "dogwifhat",
          "marketCap": 149569660,
          "open": 0.14872549164657825,
          "high": 0.151691,
          "low": 0.147801,
          "close": 0.14978,
          "returnPct": 0.007090300000000001,
          "amplitude": 0.02631917240072812,
          "volatility": 0.01315958620036406,
          "returnPct7d": -0.13422785074653198,
          "returnPct30d": -0.06953276769751608,
          "isMainstream": false
        },
        {
          "id": "official-trump",
          "symbol": "TRUMP",
          "name": "Official Trump",
          "marketCap": 363787671,
          "open": 1.5493793267430365,
          "high": 1.58,
          "low": 1.52,
          "close": 1.53,
          "returnPct": -0.0125078,
          "amplitude": 0.03947368421052633,
          "volatility": 0.019736842105263164,
          "returnPct7d": -0.10840922474951074,
          "returnPct30d": -0.30926364899135356,
          "isMainstream": true
        },
        {
          "id": "shiba-inu",
          "symbol": "SHIB",
          "name": "Shiba Inu",
          "marketCap": 2428089012,
          "open": 0.000004225461172678291,
          "high": 0.00000428,
          "low": 0.00000409,
          "close": 0.00000412,
          "returnPct": -0.024958499999999998,
          "amplitude": 0.046454767726161306,
          "volatility": 0.023227383863080653,
          "returnPct7d": -0.07012334913983466,
          "returnPct30d": -0.17676753367321382,
          "isMainstream": true
        },
        {
          "id": "bonk",
          "symbol": "BONK",
          "name": "Bonk",
          "marketCap": 320789158,
          "open": 0.000003948352940232132,
          "high": 0.00000402,
          "low": 0.00000365,
          "close": 0.00000364,
          "returnPct": -0.0780966,
          "amplitude": 0.10136986301369855,
          "volatility": 0.05068493150684927,
          "returnPct7d": -0.18826697953517205,
          "returnPct30d": -0.19719158278956647,
          "isMainstream": true
        },
        {
          "id": "floki",
          "symbol": "FLOKI",
          "name": "FLOKI",
          "marketCap": 209924473,
          "open": 0.000022351156805896433,
          "high": 0.00002266,
          "low": 0.00002169,
          "close": 0.00002176,
          "returnPct": -0.0264486,
          "amplitude": 0.04472106961733524,
          "volatility": 0.02236053480866762,
          "returnPct7d": -0.07817710801785885,
          "returnPct30d": -0.13429794495503913,
          "isMainstream": false
        }
      ]
    },
    {
      "id": "privacy",
      "name": "隐私币",
      "totalMarketCap": 14694182635,
      "weightedReturnPct": -0.0530573888872641,
      "weightedAmplitude": 0.07476092552681939,
      "weightedVolatility": 0.03738046276340969,
      "weightedReturnPct7d": 0.03674917424121995,
      "weightedReturnPct30d": 0.059044605581413445,
      "coins": [
        {
          "id": "monero",
          "symbol": "XMR",
          "name": "Monero",
          "marketCap": 6017890693,
          "open": 326.14653513066725,
          "high": 332.85,
          "low": 318.6,
          "close": 320.48,
          "returnPct": -0.0173742,
          "amplitude": 0.04472693032015074,
          "volatility": 0.02236346516007537,
          "returnPct7d": -0.012900606807058375,
          "returnPct30d": -0.05691537525913622,
          "isMainstream": true
        },
        {
          "id": "zcash",
          "symbol": "ZEC",
          "name": "Zcash",
          "marketCap": 8259142104,
          "open": 534.2218930187751,
          "high": 538.64,
          "low": 491.15,
          "close": 491.88,
          "returnPct": -0.07925900000000001,
          "amplitude": 0.09669143846075534,
          "volatility": 0.04834571923037767,
          "returnPct7d": 0.07855389156448996,
          "returnPct30d": 0.15068005606061402,
          "isMainstream": true
        },
        {
          "id": "dash",
          "symbol": "DASH",
          "name": "Dash",
          "marketCap": 417149838,
          "open": 34.36618728920082,
          "high": 35.05,
          "low": 32.64,
          "close": 32.68,
          "returnPct": -0.0490653,
          "amplitude": 0.0738357843137254,
          "volatility": 0.0369178921568627,
          "returnPct7d": -0.074683556821031,
          "returnPct30d": -0.08238111831152092,
          "isMainstream": true
        }
      ]
    },
    {
      "id": "rwa",
      "name": "RWA",
      "totalMarketCap": 1500801491,
      "weightedReturnPct": -0.0432245,
      "weightedAmplitude": 0.058149791164033626,
      "weightedVolatility": 0.029074895582016813,
      "weightedReturnPct7d": -0.08330809890420648,
      "weightedReturnPct30d": -0.1594692888911746,
      "coins": [
        {
          "id": "ondo-finance",
          "symbol": "ONDO",
          "name": "Ondo",
          "marketCap": 1500801491,
          "open": 0.32213931063243156,
          "high": 0.326308,
          "low": 0.308376,
          "close": 0.308215,
          "returnPct": -0.0432245,
          "amplitude": 0.058149791164033626,
          "volatility": 0.029074895582016813,
          "returnPct7d": -0.08330809890420648,
          "returnPct30d": -0.1594692888911746,
          "isMainstream": true
        }
      ]
    },
    {
      "id": "btc-eco",
      "name": "BTC 生态",
      "totalMarketCap": 376511930,
      "weightedReturnPct": -0.036409500000000004,
      "weightedAmplitude": 0.0572551499259204,
      "weightedVolatility": 0.0286275749629602,
      "weightedReturnPct7d": -0.04700285114321029,
      "weightedReturnPct30d": -0.11790220887339772,
      "coins": [
        {
          "id": "ordinals",
          "symbol": "ORDI",
          "name": "ORDI",
          "marketCap": 73028003,
          "open": 3.5194242383758625,
          "high": 3.65,
          "low": 3.43,
          "close": 3.48,
          "returnPct": -0.0112019,
          "amplitude": 0.06413994169096204,
          "volatility": 0.03206997084548102,
          "returnPct7d": -0.007329533779825504,
          "returnPct30d": 0.02446085296970411,
          "isMainstream": false
        },
        {
          "id": "blockstack",
          "symbol": "STX",
          "name": "Stacks",
          "marketCap": 303483927,
          "open": 0.17000686494937423,
          "high": 0.170549,
          "low": 0.161313,
          "close": 0.163817,
          "returnPct": -0.036409500000000004,
          "amplitude": 0.0572551499259204,
          "volatility": 0.0286275749629602,
          "returnPct7d": -0.04700285114321029,
          "returnPct30d": -0.11790220887339772,
          "isMainstream": true
        }
      ]
    },
    {
      "id": "infra",
      "name": "基础设施",
      "totalMarketCap": 6012562472,
      "weightedReturnPct": -0.0190029,
      "weightedAmplitude": 0.0397435897435896,
      "weightedVolatility": 0.0198717948717948,
      "weightedReturnPct7d": -0.02982703812706194,
      "weightedReturnPct30d": -0.021331664924465376,
      "coins": [
        {
          "id": "chainlink",
          "symbol": "LINK",
          "name": "Chainlink",
          "marketCap": 5847925605,
          "open": 7.971481261259591,
          "high": 8.11,
          "low": 7.8,
          "close": 7.82,
          "returnPct": -0.0190029,
          "amplitude": 0.0397435897435896,
          "volatility": 0.0198717948717948,
          "returnPct7d": -0.02982703812706194,
          "returnPct30d": -0.021331664924465376,
          "isMainstream": true
        },
        {
          "id": "ethereum-name-service",
          "symbol": "ENS",
          "name": "Ethereum Name Service",
          "marketCap": 164636867,
          "open": 4.09332080756852,
          "high": 4.15,
          "low": 4.01,
          "close": 4.03,
          "returnPct": -0.015469299999999998,
          "amplitude": 0.034912718204488824,
          "volatility": 0.017456359102244412,
          "returnPct7d": -0.06656120815860207,
          "returnPct30d": -0.18943680356531797,
          "isMainstream": false
        }
      ]
    },
    {
      "id": "other",
      "name": "其他主流",
      "totalMarketCap": 826957811,
      "weightedReturnPct": -0.1612036,
      "weightedAmplitude": 0.213590163716048,
      "weightedVolatility": 0.106795081858024,
      "weightedReturnPct7d": -0.3341965851813519,
      "weightedReturnPct30d": -0.4285259304365913,
      "coins": [
        {
          "id": "pi-network",
          "symbol": "PI",
          "name": "Pi Network",
          "marketCap": 826957811,
          "open": 0.09032346824569108,
          "high": 0.091103,
          "low": 0.075069,
          "close": 0.075763,
          "returnPct": -0.1612036,
          "amplitude": 0.213590163716048,
          "volatility": 0.106795081858024,
          "returnPct7d": -0.3341965851813519,
          "returnPct30d": -0.4285259304365913,
          "isMainstream": true
        }
      ]
    }
  ]
}